Workbook
Name UPDATE: 'Data Sheet'!$E$1

Sheet  Model>

Sheet 3 Statement Model
C2: Historical Data | H2: Forecast Period
C3: ='Historical FS'!H3 -> 44651 | D3: ='Historical FS'!I3 -> 45016 | E3: ='Historical FS'!J3 -> 45382 | F3: ='Historical FS'!K3 -> 45747 | G3: ='Historical FS'!L3 -> 46112 | H3: =G3+365 -> 46477 | I3: =H3+365 -> 46842 | J3: =I3+365 -> 47207 | K3: =J3+365 -> 47572 | L3: =K3+365 -> 47937
B4: Balance Sheet Check | C4: =IF(C46=C59,"True","False") -> True | D4: =IF(D46=D59,"True","False") -> True | E4: =IF(E46=E59,"True","False") -> True | F4: =IF(F46=F59,"True","False") -> True | G4: =IF(G46=G59,"True","False") -> True | H4: =IF(H46=H59,"True","False") -> True | I4: =IF(I46=I59,"True","False") -> True | J4: =IF(J46=J59,"True","False") -> True | ... L4: =IF(L46=L59,"True","False") -> True
A6: # | B6: Assumptions
B7: Sales (% Growth) | D7: =D27/C27-1 -> 0.20655864 | E7: =E27/D27-1 -> 0.047033734 | F7: =F27/E27-1 -> 0.060649444 | G7: =G27/F27-1 -> 0.096079514 | H7: 0.106 | I7: 0.106 | J7: 0.106 | K7: 0.106 | L7: 0.106
B8: COGS (% Revenue | C8: =C28/C27 -> 0.69728957 | D8: =D28/D27 -> 0.71460206 | E8: =E28/E27 -> 0.71601484 | F8: =F28/F27 -> 0.71528928 | G8: =G28/G27 -> 0.71792331 | H8: 0.7122 | I8: 0.7122 | J8: 0.7122 | K8: 0.7122 | L8: 0.7122
B9: Selling & Adm Expense(% Revenue) | C9: =C30/C27 -> 0.043825684 | D9: =D30/D27 -> 0.04603896 | E9: =E30/E27 -> 0.046951259 | F9: =F30/F27 -> 0.043984294 | G9: =G30/G27 -> 0.045412818 | H9: 0.0452 | I9: 0.0452 | J9: 0.0452 | K9: 0.0452 | L9: 0.0452
B10: Other Income % Of Revenue | C10: =C32/C27 -> 0.018866994 | D10: =D32/D27 -> 0.01840332 | E10: =E32/E27 -> 0.030656602 | F10: =F32/F27 -> 0.022087245 | G10: =G32/G27 -> 0.01697733 | H10: 0.021 | I10: 0.021 | J10: 0.021 | K10: 0.021 | L10: 0.021
B11: Depreciation | C11: =C34/(C48+C49) -> 0.13259078 | D11: =D34/(D48+D49) -> 0.14315725 | E11: =E34/(E48+E49) -> 0.16758015 | F11: =F34/(F48+F49) -> 0.15143981 | G11: =G34/(G48+G49) -> 0.14293212 | H11: 0.1475 | I11: 0.1475 | J11: 0.1475 | K11: 0.1475 | L11: 0.1475
B12: Interest | C12: =C35/C44 -> 0.036536354 | D12: =D35/D44 -> 0.03422099 | E12: =E35/E44 -> 0.056226821 | F12: =F35/F44 -> 0.050565212 | G12: =G35/G44 -> 0.045335658 | H12: 0.045 | I12: 0.045 | J12: 0.045 | K12: 0.045 | L12: 0.045
B13: Tax (% EBT | C13: =C37/C36 -> 0.26449684 | D13: =D37/D36 -> 0.27651401 | E13: =E37/E36 -> 0.27064577 | F13: =F37/F36 -> 0.28871517 | G13: =G37/G36 -> 0.26305788 | H13: 0.2727 | I13: 0.2727 | J13: 0.2727 | K13: 0.2727 | L13: 0.2727
B14: Accounts Receivables (days) | C14: =C54/C27*C24 -> 68.108368 | D14: =D54/D27*D24 -> 63.227837 | E14: =E54/E27*E24 -> 71.715006 | F14: =F54/F27*F24 -> 69.775262 | G14: =G54/G27*G24 -> 71.986622 | H14: 68 | I14: 68 | J14: 68 | K14: 68 | L14: 68
B15: Inventory (days) | C15: =C55/C27*C24 -> 0 | D15: =D55/D27*D24 -> 0 | E15: =E55/E27*E24 -> 0 | F15: =F55/F27*F24 -> 0 | G15: =G55/G27*G24 -> 0 | H15: 0 | I15: 0 | J15: 0 | K15: 0 | L15: 0
B16: Accounts Payables (days) | C16: =C44/C27*C24 -> 16.425465 | D16: =D44/D27*D24 -> 20.639074 | E16: =E44/E27*E24 -> 19.854461 | F16: =F44/F27*F24 -> 18.423554 | G16: =G44/G27*G24 -> 18.747495 | H16: 18 | I16: 18 | J16: 18 | K16: 18 | L16: 18
B17: Capex % of Revenue | C17: =C96/C27 -> 0.03100106 | D17: =D96/D27 -> 0.052123434 | E17: =E96/E27 -> 0.020010412 | F17: =F96/F27 -> 0.050009203 | G17: =G96/G27 -> 0.043162608 | H17: 0.04 | I17: 0.04 | J17: 0.04 | K17: 0.04 | L17: 0.04
B18: CWIP | C18: =C49 -> 416 | D18: =D49 -> 288 | E18: =E49 -> 293 | F18: =F49 -> 814 | G18: =G49 -> 526 | H18: 467 | I18: 467 | J18: 467 | K18: 467 | L18: 467
B19: Other Liabilities % Of Revenue | C19: =C45/C27 -> 0.29517186 | D19: =D45/D27 -> 0.27860486 | E19: =E45/E27 -> 0.25733715 | F19: =F45/F27 -> 0.26842138 | G19: =G45/G27 -> 0.29252729 | H19: 0.2784 | I19: 0.2784 | J19: 0.2784 | K19: 0.2784 | L19: 0.2784
B20: Other Non Current Assets % Of Revenue | C20: =C51/C27 -> 0.24678357 | D20: =D51/D27 -> 0.2589683 | E20: =E51/E27 -> 0.25055639 | F20: =F51/F27 -> 0.22618566 | G20: =G51/G27 -> 0.22769102 | H20: 0.23 | I20: 0.23 | J20: 0.23 | K20: 0.23 | L20: 0.23
B21: Investment Growth Rate | D21: =D50/C50-1 -> -0.041625664 | E21: =E50/D50-1 -> 0.26414416 | F21: =F50/E50-1 -> -0.043942655 | G21: =G50/F50-1 -> -0.07055775 | H21: 0.027 | I21: 0.027 | J21: 0.027 | K21: 0.027 | L21: 0.027
B22: Equity Share Capital | C22: =C42 -> 2098 | D22: =D42 -> 2069 | E22: =E42 -> 2071 | F22: =F42 -> 2073 | G22: =G42 -> 2024 | H22: 2024 | I22: 2024 | J22: 2024 | K22: 2024 | L22: 2024
B23: Dividend Payout Ratio | D23: =D112 -> 0.0035672806 | E23: =E112 -> 0.48411308 | F23: =F112 -> 0.28785047 | G23: =G112 -> -0.098968582 | H23: 0.1691 | I23: 0.1691 | J23: 0.1691 | K23: 0.1691 | L23: 0.1691
B24: Period | C24: 365 | D24: 365 | E24: 365 | F24: 365 | G24: 365 | H24: 365 | I24: 365 | J24: 365 | K24: 365 | L24: 365
A26: # | B26: Income Statement
B27: Sales | C27: 121641 | D27: 146767 | E27: 153670 | F27: 162990 | G27: 178650 | H27: =G27*(1+H7) -> 197586.9 | I27: =H27*(1+I7) -> 218531.11 | J27: =I27*(1+J7) -> 241695.41 | K27: =J27*(1+K7) -> 267315.12 | L27: =K27*(1+L7) -> 295650.53
B28: COGS | C28: 84819 | D28: 104880 | E28: 110030 | F28: 116585 | G28: 128257 | H28: =H27*H8 -> 140721.39 | I28: =I27*I8 -> 155637.86 | J28: =J27*J8 -> 172135.47 | K28: =K27*K8 -> 190381.83 | L28: =L27*L8 -> 210562.3
B29: Gross Profits | C29: =C27-C28 -> 36822 | D29: =D27-D28 -> 41887 | E29: =E27-E28 -> 43640 | F29: =F27-F28 -> 46405 | G29: =G27-G28 -> 50393 | H29: =H27-H28 -> 56865.51 | I29: =I27-I28 -> 62893.254 | J29: =J27-J28 -> 69559.939 | ... L29: =L27-L28 -> 85088.221
B30: Selling & Adm Expense | C30: 5331 | D30: 6757 | E30: 7215 | F30: 7169 | G30: 8113 | H30: =H27*H9 -> 8930.9279 | I30: =I27*I9 -> 9877.6062 | J30: =J27*J9 -> 10924.632 | K30: =K27*K9 -> 12082.644 | L30: =L27*L9 -> 13363.404
B31: EBITDA | C31: =C29-C30 -> 31491 | D31: =D29-D30 -> 35130 | E31: =E29-E30 -> 36425 | F31: =F29-F30 -> 39236 | G31: =G29-G30 -> 42280 | H31: =H29-H30 -> 47934.582 | I31: =I29-I30 -> 53015.648 | J31: =J29-J30 -> 58635.306 | ... L31: =L29-L30 -> 71724.818
B32: Other Income | C32: 2295 | D32: 2701 | E32: 4711 | F32: 3600 | G32: 3033 | H32: =H27*H10 -> 4149.3249 | I32: =I27*I10 -> 4589.1533 | J32: =J27*J10 -> 5075.6036 | K32: =K27*K10 -> 5613.6176 | L32: =L27*L10 -> 6208.661
B33: Expenses
B34: Depreciation | C34: 3476 | D34: 4225 | E34: 4678 | F34: 4812 | G34: 4902 | H34: =H97 -> 4981.075 | I34: =I97 -> 5412.1291 | J34: =J97 -> 5903.1737 | K34: =K97 -> 6458.4585 | L34: =L97 -> 7082.9951
B35: Interest | C35: 200 | D35: 284 | E35: 470 | F35: 416 | G35: 416 | H35: =H104 -> 412.92 | I35: =I104 -> 438.48052 | J35: =J104 -> 484.95945 | K35: =K104 -> 536.36515 | L35: =L104 -> 593.21986
B36: EBT | C36: =C31+C32-(C34+C35) -> 30110 | D36: =D31+D32-(D34+D35) -> 33322 | E36: =E31+E32-(E34+E35) -> 35988 | F36: =F31+F32-(F34+F35) -> 37608 | G36: =G31+G32-(G34+G35) -> 39995 | H36: =H31+H32-(H34+H35) -> 46689.912 | I36: =I31+I32-(I34+I35) -> 51754.191 | J36: =J31+J32-(J34+J35) -> 57322.777 | ... L36: =L31+L32-(L34+L35) -> 70257.264
B37: Tax | C37: 7964 | D37: 9214 | E37: 9740 | F37: 10858 | G37: 10521 | H37: =H36*H13 -> 12732.339 | I37: =I36*I13 -> 14113.368 | J37: =J36*J13 -> 15631.921 | K37: =K36*K13 -> 17308.117 | L37: =L36*L13 -> 19159.156
B38: Net Profits | C38: =C36-C37 -> 22146 | D38: =D36-D37 -> 24108 | E38: =E36-E37 -> 26248 | F38: =F36-F37 -> 26750 | G38: =G36-G37 -> 29474 | H38: =H36-H37 -> 33957.573 | I38: =I36-I37 -> 37640.823 | J38: =J36-J37 -> 41690.856 | ... L38: =L36-L37 -> 51098.108
A41: # | B41: Balance Sheet
B42: Equity Share Capital | C42: 2098 | D42: 2069 | E42: 2071 | F42: 2073 | G42: 2024 | H42: =H22 -> 2024 | I42: =I22 -> 2024 | J42: =J22 -> 2024 | K42: =K22 -> 2024 | L42: =L22 -> 2024
B43: Reserves | C43: 73252 | D43: 73338 | E43: 86045 | F43: 93745 | G43: 90828 | H43: =H111 -> 119043.35 | I43: =I111 -> 150319.11 | J43: =J111 -> 184960.04 | K43: =K111 -> 223315.48 | L43: =L111 -> 265772.9
B44: Borrowings | C44: 5474 | D44: 8299 | E44: 8359 | F44: 8227 | G44: 9176 | H44: =H27*H16/H24 -> 9744.0115 | I44: =I27*I16/I24 -> 10776.877 | J44: =J27*J16/J24 -> 11919.226 | K44: =K27*K16/K24 -> 13182.664 | L44: =L27*L16/L24 -> 14580.026
B45: Other Liabilities | C45: 35905 | D45: 40890 | E45: 39545 | F45: 43750 | G45: 52260 | H45: =G45*(1+H19) -> 66809.184 | I45: =H45*(1+I19) -> 85408.861 | J45: =I45*(1+J19) -> 109186.69 | K45: =J45*(1+K19) -> 139584.26 | L45: =K45*(1+L19) -> 178444.52
B46: Total liablities | C46: =SUM(C42:C45) -> 116729 | D46: =SUM(D42:D45) -> 124596 | E46: =SUM(E42:E45) -> 136020 | F46: =SUM(F42:F45) -> 147795 | G46: =SUM(G42:G45) -> 154288 | H46: =SUM(H42:H45) -> 197620.54 | I46: =SUM(I42:I45) -> 248528.84 | J46: =SUM(J42:J45) -> 308089.95 | ... L46: =SUM(L42:L45) -> 460821.45
B48: Fixed Assets Net Block | C48: 25800 | D48: 29225 | E48: 27622 | F48: 30961 | G48: 33770 | H48: =H98 -> 36692.401 | I48: =I98 -> 40021.516 | J48: =J98 -> 43786.159 | K48: =K98 -> 48020.305 | L48: =L98 -> 52763.331
B49: Capital Work in Progress | C49: 416 | D49: 288 | E49: 293 | F49: 814 | G49: 526 | H49: =H18 -> 467 | I49: =I18 -> 467 | J49: =J18 -> 467 | K49: =K18 -> 467 | L49: =L18 -> 467
B50: Investments | C50: 20324 | D50: 19478 | E50: 24623 | F50: 23541 | G50: 21880 | H50: =G50*(1+H21) -> 22470.76 | I50: =H50*(1+I21) -> 23077.471 | J50: =I50*(1+J21) -> 23700.562 | K50: =J50*(1+K21) -> 24340.477 | L50: =K50*(1+L21) -> 24997.67
B51: Other Assets | C51: 30019 | D51: 38008 | E51: 38503 | F51: 36866 | G51: 40677 | H51: =G51*(1+H20) -> 50032.71 | I51: =H51*(1+I20) -> 61540.233 | J51: =I51*(1+J20) -> 75694.487 | K51: =J51*(1+K20) -> 93104.219 | L51: =K51*(1+L20) -> 114518.19
B52: Total Non Current Assets | C52: =SUM(C48:C51) -> 76559 | D52: =SUM(D48:D51) -> 86999 | E52: =SUM(E48:E51) -> 91041 | F52: =SUM(F48:F51) -> 92182 | G52: =SUM(G48:G51) -> 96853 | H52: =SUM(H48:H51) -> 109662.87 | I52: =SUM(I48:I51) -> 125106.22 | J52: =SUM(J48:J51) -> 143648.21 | ... L52: =SUM(L48:L51) -> 192746.19
B54: Receivables | C54: 22698 | D54: 25424 | E54: 30193 | F54: 31158 | G54: 35234 | H54: =H27*H14/H24 -> 36810.71 | I54: =I27*I14/I24 -> 40712.645 | J54: =J27*J14/J24 -> 45028.186 | K54: =K27*K14/K24 -> 49801.174 | L54: =L27*L14/L24 -> 55080.098
B55: Inventory | C55: 0 | D55: 0 | E55: 0 | F55: 0 | G55: 0 | H55: =H27*H15/H24 -> 0 | I55: =I27*I15/I24 -> 0 | J55: =J27*J15/J24 -> 0 | K55: =K27*K15/K24 -> 0 | L55: =L27*L15/L24 -> 0
B56: Cash & Bank | C56: 17472 | D56: 12173 | E56: 14786 | F56: 24455 | G56: 22201 | H56: =H81 -> 51146.962 | I56: =I81 -> 82709.979 | J56: =J81 -> 119413.56 | K56: =K81 -> 162373.23 | L56: =L81 -> 212995.16
B57: Total Current Assets | C57: =SUM(C54:C56) -> 40170 | D57: =SUM(D54:D56) -> 37597 | E57: =SUM(E54:E56) -> 44979 | F57: =SUM(F54:F56) -> 55613 | G57: =SUM(G54:G56) -> 57435 | H57: =SUM(H54:H56) -> 87957.672 | I57: =SUM(I54:I56) -> 123422.62 | J57: =SUM(J54:J56) -> 164441.74 | ... L57: =SUM(L54:L56) -> 268075.26
B59: Total Assets | C59: =SUM(C52,C57) -> 116729 | D59: =SUM(D52,D57) -> 124596 | E59: =SUM(E52,E57) -> 136020 | F59: =SUM(F52,F57) -> 147795 | G59: =SUM(G52,G57) -> 154288 | H59: =H57+H52 -> 197620.54 | I59: =I57+I52 -> 248528.84 | J59: =J57+J52 -> 308089.95 | K59: =K57+K52 -> 378106.41 | L59: =L57+L52 -> 460821.45
A62: # | B62: Cash Flow Statement
B64: Cash from Operating Activity | C64: 23885 | D64: 22467 | E64: 25210 | F64: 35694 | G64: 33986 | H64: =H65+H66-H67 -> 37929.949 | I64: =I65+I66-I67 -> 40183.882 | J64: =J65+J66-J67 -> 44420.838 | K64: =K65+K66-K67 -> 49110.234 | L64: =L65+L66-L67 -> 54299.541
B65: Net Profit | H65: =H38 -> 33957.573 | I65: =I38 -> 37640.823 | J65: =J38 -> 41690.856 | K65: =K38 -> 46161.326 | L65: =L38 -> 51098.108
B66: Add. Depreciation | H66: =H34 -> 4981.075 | I66: =I34 -> 5412.1291 | J66: =J34 -> 5903.1737 | K66: =K34 -> 6458.4585 | L66: =L34 -> 7082.9951
B67: Less. CIWC | H67: =H91 -> 1008.6986 | I67: =I91 -> 2869.0701 | J67: =J91 -> 3173.1915 | K67: =K91 -> 3509.5498 | L67: =L91 -> 3881.5621
B69: Cash from Investing Activity | C69: -6485 | D69: -1071 | E69: -5093 | F69: -1864 | G69: 3546 | H69: =-H70-H71-H72-H73 -> -17790.946 | I69: =-I70-I71-I72 -> -20855.478 | J69: =-J70-J71-J72 -> -24445.162 | K69: =-K70-K71-K72 -> -28742.252 | L69: =-L70-L71-L72 -> -33897.184
B70: Capex | H70: =H96 -> 7903.476 | I70: =I96 -> 8741.2445 | J70: =J96 -> 9667.8164 | K70: =K96 -> 10692.605 | L70: =L96 -> 11826.021
B71: Addition In Investments | H71: =H50-G50 -> 590.76 | I71: =I50-H50 -> 606.71052 | J71: =J50-I50 -> 623.0917 | K71: =K50-J50 -> 639.91518 | L71: =L50-K50 -> 657.19289
B72: Change In Other Assets | H72: =H51-G51 -> 9355.71 | I72: =I51-H51 -> 11507.523 | J72: =J51-I51 -> 14154.254 | K72: =K51-J51 -> 17409.732 | L72: =L51-K51 -> 21413.97
B73: CWIP | H73: =H49-G49 -> -59 | I73: =I49-H49 -> 0 | J73: =J49-I49 -> 0 | K73: =K49-J49 -> 0 | L73: =L49-K49 -> 0
B75: Cash from Financing Activity | C75: -24642 | D75: -26695 | E75: -17504 | F75: -24161 | G75: -39786 | H75: =H76-H77 -> 8806.9584 | I75: =I76-I77 -> 12234.614 | J75: =J76-J77 -> 16727.903 | K75: =K76-K77 -> 22591.694 | L75: =L76-L77 -> 30219.568
B76: Change In Other Liablities | H76: =H45-G45 -> 14549.184 | I76: =I45-H45 -> 18599.677 | J76: =J45-I45 -> 23777.827 | K76: =K45-J45 -> 30397.574 | L76: =L45-K45 -> 38860.258
B77: Dividend Paid | H77: =H110 -> 5742.2256 | I77: =I110 -> 6365.0632 | J77: =J110 -> 7049.9237 | K77: =K110 -> 7805.8802 | L77: =L110 -> 8640.69
B79: Net Cash Flow | C79: =SUM(C64,C69,C75) -> -7242 | D79: =SUM(D64,D69,D75) -> -5299 | E79: =SUM(E64,E69,E75) -> 2613 | F79: =SUM(F64,F69,F75) -> 9669 | G79: =SUM(G64,G69,G75) -> -2254 | H79: =H64+H69+H75 -> 28945.962 | I79: =I64+I69+I75 -> 31563.018 | J79: =J64+J69+J75 -> 36703.579 | K79: =K64+K69+K75 -> 42959.676 | L79: =L64+L69+L75 -> 50621.925
B80: Opening Cash Balance | H80: =G56 -> 22201 | I80: =H81 -> 51146.962 | J80: =I81 -> 82709.979 | K80: =J81 -> 119413.56 | L80: =K81 -> 162373.23
B81: Closing Cash Balance | H81: =H79+H80 -> 51146.962 | I81: =I79+I80 -> 82709.979 | J81: =J79+J80 -> 119413.56 | K81: =K79+K80 -> 162373.23 | L81: =L79+L80 -> 212995.16
A84: # | B84: Supporting Schedules
B86: Working Capital Schedule
B87: Receivables | C87: =C54 -> 22698 | D87: =D54 -> 25424 | E87: =E54 -> 30193 | F87: =F54 -> 31158 | G87: =G54 -> 35234 | H87: =H54 -> 36810.71 | I87: =I54 -> 40712.645 | J87: =J54 -> 45028.186 | ... L87: =L54 -> 55080.098
B88: Inventory | C88: =C55 -> 0 | D88: =D55 -> 0 | E88: =E55 -> 0 | F88: =F55 -> 0 | G88: =G55 -> 0 | H88: =H55 -> 0 | I88: =I55 -> 0 | J88: =J55 -> 0 | ... L88: =L55 -> 0
B89: Borrowings | C89: =C44 -> 5474 | D89: =D44 -> 8299 | E89: =E44 -> 8359 | F89: =F44 -> 8227 | G89: =G44 -> 9176 | H89: =H44 -> 9744.0115 | I89: =I44 -> 10776.877 | J89: =J44 -> 11919.226 | ... L89: =L44 -> 14580.026
B90: Net Working Capital | C90: =C87+C88-C89 -> 17224 | D90: =D87+D88-D89 -> 17125 | E90: =E87+E88-E89 -> 21834 | F90: =F87+F88-F89 -> 22931 | G90: =G87+G88-G89 -> 26058 | H90: =H87+H88-H89 -> 27066.699 | I90: =I87+I88-I89 -> 29935.769 | J90: =J87+J88-J89 -> 33108.96 | ... L90: =L87+L88-L89 -> 40500.072
B91: Change In Working Capital | D91: =D90-C90 -> -99 | E91: =E90-D90 -> 4709 | F91: =F90-E90 -> 1097 | G91: =G90-F90 -> 3127 | H91: =H90-G90 -> 1008.6986 | I91: =I90-H90 -> 2869.0701 | J91: =J90-I90 -> 3173.1915 | K91: =K90-J90 -> 3509.5498 | L91: =L90-K90 -> 3881.5621
B94: Depreciation Schedule
B95: PPE Opening Bal. | C95: 25505 | D95: =C98 -> 25800 | E95: =D98 -> 29225 | F95: =E98 -> 27622 | G95: =F98 -> 30961 | H95: =G98 -> 33770 | I95: =H98 -> 36692.401 | J95: =I98 -> 40021.516 | K95: =J98 -> 43786.159 | L95: =K98 -> 48020.305
B96: Capex | C96: =C98-C95+C97 -> 3771 | D96: =D98-D95+D97 -> 7650 | E96: =E98-E95+E97 -> 3075 | F96: =F98-F95+F97 -> 8151 | G96: =G98-G95+G97 -> 7711 | H96: =H17*H27 -> 7903.476 | I96: =I17*I27 -> 8741.2445 | J96: =J17*J27 -> 9667.8164 | K96: =K17*K27 -> 10692.605 | L96: =L17*L27 -> 11826.021
B97: Depreciation | C97: =C34 -> 3476 | D97: =D34 -> 4225 | E97: =E34 -> 4678 | F97: =F34 -> 4812 | G97: =G34 -> 4902 | H97: =H95*H11 -> 4981.075 | I97: =I95*I11 -> 5412.1291 | J97: =J95*J11 -> 5903.1737 | K97: =K95*K11 -> 6458.4585 | L97: =L95*L11 -> 7082.9951
B98: PPE Closing Bal. | C98: =C48 -> 25800 | D98: =D48 -> 29225 | E98: =E48 -> 27622 | F98: =F48 -> 30961 | G98: =G48 -> 33770 | H98: =H95-H97+H96 -> 36692.401 | I98: =I95-I97+I96 -> 40021.516 | J98: =J95-J97+J96 -> 43786.159 | K98: =K95-K97+K96 -> 48020.305 | L98: =L95-L97+L96 -> 52763.331
B100: Debt & Interest Schedule
B101: Debt Opening | C101: 5325 | D101: =C103 -> 5474 | E101: =D103 -> 8299 | F101: =E103 -> 8359 | G101: =F103 -> 8227 | H101: =G103 -> 9176 | I101: =H103 -> 9744.0115 | J101: =I103 -> 10776.877 | K101: =J103 -> 11919.226 | L101: =K103 -> 13182.664
B102: Repayments | C102: =C103-C101 -> 149 | D102: =D103-D101 -> 2825 | E102: =E103-E101 -> 60 | F102: =F103-F101 -> -132 | G102: =G103-G101 -> 949 | H102: =H103-H101 -> 568.01151 | I102: =I103-I101 -> 1032.8652 | J102: =J103-J101 -> 1142.3489 | ... L102: =L103-L101 -> 1397.3623
B103: Debt Closing | C103: =C44 -> 5474 | D103: =D44 -> 8299 | E103: =E44 -> 8359 | F103: =F44 -> 8227 | G103: =G44 -> 9176 | H103: =H44 -> 9744.0115 | I103: =I44 -> 10776.877 | J103: =J44 -> 11919.226 | ... L103: =L44 -> 14580.026
B104: Interest Exp. | C104: =C35 -> 200 | D104: =D35 -> 284 | E104: =E35 -> 470 | F104: =F35 -> 416 | G104: =G35 -> 416 | H104: =H101*H105 -> 412.92 | I104: =I101*I105 -> 438.48052 | J104: =J101*J105 -> 484.95945 | K104: =K101*K105 -> 536.36515 | L104: =L101*L105 -> 593.21986
B105: Interest Rate | C105: =C104/C101 -> 0.037558685 | D105: =D104/D101 -> 0.051881622 | E105: =E104/E101 -> 0.056633329 | F105: =F104/F101 -> 0.049766719 | G105: =G104/G101 -> 0.050565212 | H105: =H12 -> 0.045 | I105: =I12 -> 0.045 | J105: =J12 -> 0.045 | K105: =K12 -> 0.045 | L105: =L12 -> 0.045
B107: Reserves & Dividend Schedule
B108: Opening Reserves | C108: 74227 | D108: =C111 -> 73252 | E108: =D111 -> 73338 | F108: =E111 -> 86045 | G108: =F111 -> 93745 | H108: =G111 -> 90828 | I108: =H111 -> 119043.35 | J108: =I111 -> 150319.11 | K108: =J111 -> 184960.04 | L108: =K111 -> 223315.48
B109: Profits | C109: =C38 -> 22146 | D109: =D38 -> 24108 | E109: =E38 -> 26248 | F109: =F38 -> 26750 | G109: =G38 -> 29474 | H109: =H38 -> 33957.573 | I109: =I38 -> 37640.823 | J109: =J38 -> 41690.856 | ... L109: =L38 -> 51098.108
B110: Dividend Paid | D110: =D111-D108 -> 86 | E110: =E111-E108 -> 12707 | F110: =F111-F108 -> 7700 | G110: =G111-G108 -> -2917 | H110: =H109*H112 -> 5742.2256 | I110: =I109*I112 -> 6365.0632 | J110: =J109*J112 -> 7049.9237 | K110: =K109*K112 -> 7805.8802 | L110: =L109*L112 -> 8640.69
B111: Closing Reserves | C111: =C43 -> 73252 | D111: =D43 -> 73338 | E111: =E43 -> 86045 | F111: =F43 -> 93745 | G111: =G43 -> 90828 | H111: =H108+H109-H110 -> 119043.35 | I111: =I108+I109-I110 -> 150319.11 | J111: =J108+J109-J110 -> 184960.04 | K111: =K108+K109-K110 -> 223315.48 | L111: =L108+L109-L110 -> 265772.9
B112: Dividend Payout Ratio | D112: =D110/D109 -> 0.0035672806 | E112: =E110/E109 -> 0.48411308 | F112: =F110/F109 -> 0.28785047 | G112: =G110/G109 -> -0.098968582 | H112: =H23 -> 0.1691 | I112: =I23 -> 0.1691 | J112: =J23 -> 0.1691 | K112: =K23 -> 0.1691 | L112: =L23 -> 0.1691
A114: # | B114: Charts & Graphs
B115: Year | C115: 44651 | D115: 45016 | E115: 45382 | F115: 45747 | G115: 46112 | H115: 46477 | I115: 46842 | J115: 47207 | K115: 47572 | L115: 47937
B116: Revenue (Sales) | C116: =C27 -> 121641 | D116: =D27 -> 146767 | E116: =E27 -> 153670 | F116: =F27 -> 162990 | G116: =G27 -> 178650 | H116: =H27 -> 197586.9 | I116: =I27 -> 218531.11 | J116: =J27 -> 241695.41 | ... L116: =L27 -> 295650.53
B117: Gross Profit Margins % | C117: =C29/C27 -> 0.30271043 | D117: =D29/D27 -> 0.28539794 | E117: =E29/E27 -> 0.28398516 | F117: =F29/F27 -> 0.28471072 | G117: =G29/G27 -> 0.28207669 | H117: =H29/H27 -> 0.2878 | I117: =I29/I27 -> 0.2878 | J117: =J29/J27 -> 0.2878 | ... L117: =L29/L27 -> 0.2878
B119: Year | C119: 44651 | D119: 45016 | E119: 45382 | F119: 45747 | G119: 46112 | H119: 46477 | I119: 46842 | J119: 47207 | K119: 47572 | L119: 47937
B120: Cash From Operating Activites | C120: =C64 -> 23885 | D120: =D64 -> 22467 | E120: =E64 -> 25210 | F120: =F64 -> 35694 | G120: =G64 -> 33986 | H120: =H64 -> 37929.949 | I120: =I64 -> 40183.882 | J120: =J64 -> 44420.838 | ... L120: =L64 -> 54299.541
B121: Cash From Investing Activites | C121: =C69 -> -6485 | D121: =D69 -> -1071 | E121: =E69 -> -5093 | F121: =F69 -> -1864 | G121: =G69 -> 3546 | H121: =H69 -> -17790.946 | I121: =I69 -> -20855.478 | J121: =J69 -> -24445.162 | ... L121: =L69 -> -33897.184
B122: Cash From Financing Activites | C122: =C75 -> -24642 | D122: =D75 -> -26695 | E122: =E75 -> -17504 | F122: =F75 -> -24161 | G122: =G75 -> -39786 | H122: =H75 -> 8806.9584 | I122: =I75 -> 12234.614 | J122: =J75 -> 16727.903 | ... L122: =L75 -> 30219.568

Sheet Relative Valuation
B2: Comparable Company Valuation
B3: S.No. | C3: Name | D3: Share Price | E3: No. Eq. Shares | F3: Equity Value | G3: Enterprise Value | H3: Net Debt | I3: Revenue | J3: EBITDA | K3: Net Profit | L3: EV/Revenue | M3: EV / EBITDA | N3: P/E
B4: 1 | C4: TCS | D4: 2287 | E4: 361.81 | F4: =D4*E4 -> 827459.47 | G4: 825831.66 | H4: =G4-F4 -> -1627.81 | I4: 275859 | J4: =G4/M4 -> 78352.15 | K4: 78389 | L4: =G4/I4 -> 2.9936731 | M4: 10.54 | N4: =F4/K4 -> 10.555811
B5: 2 | C5: Infosys | D5: 1115.3 | E5: 405.81 | F5: =D5*E5 -> 452599.89 | G5: 439687.04 | H5: =G5-F5 -> -12912.853 | I5: 184582 | J5: =G5/M5 -> 48000.769 | K5: 48009 | L5: =G5/I5 -> 2.3820689 | M5: 9.16 | N5: =F5/K5 -> 9.4273968
B6: 3 | C6: HCL Technologies | D6: 1298.9 | E6: 271.37 | F6: =D6*E6 -> 352482.49 | G6: 334267.96 | H6: =G6-F6 -> -18214.533 | I6: 134374 | J6: =G6/M6 -> 29016.316 | K6: 29022 | L6: =G6/I6 -> 2.487594 | M6: 11.52 | N6: =F6/K6 -> 12.145355
B7: 4 | C7: Tech Mahindra | D7: 1586 | E7: 98.01 | F7: =D7*E7 -> 155443.86 | G7: 152522.27 | H7: =G7-F7 -> -2921.59 | I7: 59176.1 | J7: =G7/M7 -> 9544.5726 | K7: 9542.3 | L7: =G7/I7 -> 2.5774302 | M7: 15.98 | N7: =F7/K7 -> 16.289978
B8: 5 | C8: Wipro | D8: 179.15 | E8: 990.45 | F8: =D8*E8 -> 177439.12 | G8: 187175.3 | H8: =G8-F8 -> 9736.1825 | I8: 94968 | J8: =G8/M8 -> 22020.624 | K8: 22017.7 | L8: =G8/I8 -> 1.9709302 | M8: 8.5 | N8: =F8/K8 -> 8.0589307
B9: 6 | C9: LTM | D9: 4637.5 | E9: 29.66 | F9: =D9*E9 -> 137548.25 | G9: 137055.72 | H9: =G9-F9 -> -492.53 | I9: 44075 | J9: =G9/M9 -> 8922.8984 | K9: 8924.1 | L9: =G9/I9 -> 3.1096023 | M9: 15.36 | N9: =F9/K9 -> 15.413123
B10: 7 | C10: Presistent System | D10: 5520.15 | E10: 15.78 | F10: =D10*E10 -> 87107.967 | G10: 86339.56 | H10: =G10-F10 -> -768.407 | I10: 15718.1 | J10: =G10/M10 -> 3076.9622 | K10: 3077.15 | L10: =G10/I10 -> 5.4930023 | M10: 28.06 | N10: =F10/K10 -> 28.308002
B12: High | L12: =MAX(L4:L10) -> 5.4930023 | M12: =MAX(M4:M10) -> 28.06 | N12: =MAX(N4:N10) -> 28.308002
B13: 75th Percentile | L13: =QUARTILE(L4:L10,3) -> 3.0516377 | M13: =QUARTILE(M4:M10,3) -> 15.67 | N13: =QUARTILE(N4:N10,3) -> 15.851551
B14: Average | L14: =AVERAGE(L4:L10) -> 3.002043 | M14: =AVERAGE(M4:M10) -> 14.16 | N14: =AVERAGE(N4:N10) -> 14.314085
B15: Median | L15: =MEDIAN(L4:L10) -> 2.5774302 | M15: =MEDIAN(M4:M10) -> 11.52 | N15: =MEDIAN(N4:N10) -> 12.145355
B16: 25th Percentile | L16: =QUARTILE(L4:L10,1) -> 2.4348315 | M16: =QUARTILE(M4:M10,1) -> 9.85 | N16: =QUARTILE(N4:N10,1) -> 9.9916039
B17: Low | L17: =MIN(L4:L10) -> 1.9709302 | M17: =MIN(M4:M10) -> 8.5 | N17: =MIN(N4:N10) -> 8.0589307
B19: Comparable Valuation
B20: Implied Enterprise Value | L20: =L15*I5 -> 475747.23 | M20: =M15*J5 -> 552968.85 | N20: =N22+N21 -> 570173.5
B21: Net Debt | L21: =$H$5 -> -12912.853 | M21: =$H$5 -> -12912.853 | N21: =$H$5 -> -12912.853
B22: Implied Market Value | L22: =L20-L21 -> 488660.08 | M22: =M20-M21 -> 565881.71 | N22: =N15*K5 -> 583086.35
B23: No. Of Shares | L23: =$E$5 -> 405.81 | M23: =$E$5 -> 405.81 | N23: =$E$5 -> 405.81
B24: Implied Value of Shares | L24: =L22/L23 -> 1204.1598 | M24: =M22/M23 -> 1394.4499 | N24: =N22/N23 -> 1436.8457
L25: =IF(L24>$D$5,"Undervalued","Overvalued") -> Undervalued | M25: =IF(M24>$D$5,"Undervalued","Overvalued") -> Undervalued | N25: =IF(N24>$D$5,"Undervalued","Overvalued") -> Undervalued
B27: 1) Financial data is sourced from the Screener.in.
B28: 2) Minor differences may exist due to rounding of reported figures.
B29: 3) All figures are presented in Rupee Corores

Sheet DCF Valuation Model
B2: Unlevered Cash Flow
B3: Fiscal Year | F3: ='3 Statement Model'!G3 -> 46112 | G3: ='3 Statement Model'!H3 -> 46477 | H3: ='3 Statement Model'!I3 -> 46842 | I3: ='3 Statement Model'!J3 -> 47207 | J3: ='3 Statement Model'!K3 -> 47572 | K3: ='3 Statement Model'!L3 -> 47937
B4: Sales | F4: ='3 Statement Model'!G27 -> 178650 | G4: ='3 Statement Model'!H27 -> 197586.9 | H4: ='3 Statement Model'!I27 -> 218531.11 | I4: ='3 Statement Model'!J27 -> 241695.41 | J4: ='3 Statement Model'!K27 -> 267315.12 | K4: ='3 Statement Model'!L27 -> 295650.53
B5: COGS | F5: ='3 Statement Model'!G28 -> 128257 | G5: ='3 Statement Model'!H28 -> 140721.39 | H5: ='3 Statement Model'!I28 -> 155637.86 | I5: ='3 Statement Model'!J28 -> 172135.47 | J5: ='3 Statement Model'!K28 -> 190381.83 | K5: ='3 Statement Model'!L28 -> 210562.3
B6: Gross Profits | F6: =F4-F5 -> 50393 | G6: =G4-G5 -> 56865.51 | H6: =H4-H5 -> 62893.254 | I6: =I4-I5 -> 69559.939 | J6: =J4-J5 -> 76933.292 | K6: =K4-K5 -> 85088.221
B7: Selling & Adm Expense | F7: ='3 Statement Model'!G30 -> 8113 | G7: ='3 Statement Model'!H30 -> 8930.9279 | H7: ='3 Statement Model'!I30 -> 9877.6062 | I7: ='3 Statement Model'!J30 -> 10924.632 | J7: ='3 Statement Model'!K30 -> 12082.644 | K7: ='3 Statement Model'!L30 -> 13363.404
B8: EBITDA | F8: =F6-F7 -> 42280 | G8: =G6-G7 -> 47934.582 | H8: =H6-H7 -> 53015.648 | I8: =I6-I7 -> 58635.306 | J8: =J6-J7 -> 64850.649 | K8: =K6-K7 -> 71724.818
B9: Other Income | F9: ='3 Statement Model'!G32 -> 3033 | G9: ='3 Statement Model'!H32 -> 4149.3249 | H9: ='3 Statement Model'!I32 -> 4589.1533 | I9: ='3 Statement Model'!J32 -> 5075.6036 | J9: ='3 Statement Model'!K32 -> 5613.6176 | K9: ='3 Statement Model'!L32 -> 6208.661
B10: Operating Expenses
B11: Depreciation | F11: ='3 Statement Model'!G34 -> 4902 | G11: ='3 Statement Model'!H34 -> 4981.075 | H11: ='3 Statement Model'!I34 -> 5412.1291 | I11: ='3 Statement Model'!J34 -> 5903.1737 | J11: ='3 Statement Model'!K34 -> 6458.4585 | K11: ='3 Statement Model'!L34 -> 7082.9951
B12: EBIT | F12: =F8+F9-F11 -> 40411 | G12: =G8+G9-G11 -> 47102.832 | H12: =H8+H9-H11 -> 52192.672 | I12: =I8+I9-I11 -> 57807.736 | J12: =J8+J9-J11 -> 64005.808 | K12: =K8+K9-K11 -> 70850.483
B13: Tax | F13: ='3 Statement Model'!G37 -> 10521 | G13: ='3 Statement Model'!H37 -> 12732.339 | H13: ='3 Statement Model'!I37 -> 14113.368 | I13: ='3 Statement Model'!J37 -> 15631.921 | J13: ='3 Statement Model'!K37 -> 17308.117 | K13: ='3 Statement Model'!L37 -> 19159.156
B14: NOPAT | F14: =F12-F13 -> 29890 | G14: =G12-G13 -> 34370.493 | H14: =H12-H13 -> 38079.304 | I14: =I12-I13 -> 42175.815 | J14: =J12-J13 -> 46697.691 | K14: =K12-K13 -> 51691.328
B15: Add. Depreciation | F15: =F11 -> 4902 | G15: =G11 -> 4981.075 | H15: =H11 -> 5412.1291 | I15: =I11 -> 5903.1737 | J15: =J11 -> 6458.4585 | K15: =K11 -> 7082.9951
B16: Less. Capex | F16: ='3 Statement Model'!G96 -> 7711 | G16: ='3 Statement Model'!H96 -> 7903.476 | H16: ='3 Statement Model'!I96 -> 8741.2445 | I16: ='3 Statement Model'!J96 -> 9667.8164 | J16: ='3 Statement Model'!K96 -> 10692.605 | K16: ='3 Statement Model'!L96 -> 11826.021
B17: Less. Change in NWC | F17: ='3 Statement Model'!G91 -> 3127 | G17: ='3 Statement Model'!H91 -> 1008.6986 | H17: ='3 Statement Model'!I91 -> 2869.0701 | I17: ='3 Statement Model'!J91 -> 3173.1915 | J17: ='3 Statement Model'!K91 -> 3509.5498 | K17: ='3 Statement Model'!L91 -> 3881.5621
B18: Net Working Capital | F18: ='3 Statement Model'!G90 -> 26058 | G18: ='3 Statement Model'!H90 -> 27066.699 | H18: ='3 Statement Model'!I90 -> 29935.769 | I18: ='3 Statement Model'!J90 -> 33108.96 | J18: ='3 Statement Model'!K90 -> 36618.51 | K18: ='3 Statement Model'!L90 -> 40500.072
B19: Unlevered Cash Flow | F19: =F14+F15-F16-F17 -> 23954 | G19: =G14+G15-G16-G17 -> 30439.393 | H19: =H14+H15-H16-H17 -> 31881.118 | I19: =I14+I15-I16-I17 -> 35237.981 | J19: =J14+J15-J16-J17 -> 38953.995 | K19: =K14+K15-K16-K17 -> 43066.74
B20: Projection Year | G20: 1 | H20: 2 | I20: 3 | J20: 4 | K20: 5
B21: Discounting Factor | G21: =1/(1+$D$26)^G20 -> 0.89834075 | H21: =1/(1+$D$26)^H20 -> 0.8070161 | I21: =1/(1+$D$26)^I20 -> 0.72497545 | J21: =1/(1+$D$26)^J20 -> 0.65127499 | K21: =1/(1+$D$26)^K20 -> 0.58506687
B22: PV Of FCFF | G22: =G19*G21 -> 27344.947 | H22: =H19*H21 -> 25728.576 | I22: =I19*I21 -> 25546.671 | J22: =J19*J21 -> 25369.763 | K22: =K19*K21 -> 25196.922
B24: Expected Growth | D24: 0.106
B25: Terminal Growth | D25: 0.045
B26: WACC | D26: =WACC!J34 -> 0.11316335
B28: Calculation Of Terminal Value | G28: Calculation Of Value Of Operating Assets
B29: WACC | E29: =D26 -> 0.11316335 | G29: Sum Of PV Of FCFF | K29: =SUM(G22:K22) -> 129186.88
B30: Terminal Growth | E30: =D25 -> 0.045 | G30: PV Of Terminal Value | K30: =E32*K21 -> 386289.46
B32: Terminal Value | E32: =K19*(1+E30)/(E29-E30) -> 660248.4 | G32: Value Of Operating Assets | K32: =K29+K30 -> 515476.34
B34: Equity Value Per Share | H34: Sensitivity Analysis
G35: =E40 -> 1302.3509 | H35: 0.1 | I35: 0.1075 | J35: 0.1132 | K35: 0.12
B36: Add : Cash | E36: ='Data Sheet'!K69 -> 22201 | G36: 0.025 | H36: 1199.0218 | I36: 1121.8783 | J36: 1072.0237 | K36: 1020.3737
B37: Less: Debt | E37: ='Data Sheet'!K59 -> 9176 | G37: 0.035 | H37: 1339.1248 | I37: 1236.8474 | J37: 1172.2374 | K37: 1106.4939
B38: Value Of Equity | E38: =K32+E36-E37 -> 528501.34 | G38: 0.045 | H38: 1530.1744 | I38: 1388.6066 | J38: 1301.8393 | K38: 1215.5794
B39: No. Of Shares | E39: ='Data Sheet'!B6 -> 405.80565 | G39: 0.055 | H39: 1806.1349 | I39: 1598.1789 | J39: 1475.978 | K39: 1358.2298
B40: Equity Value Per Share | E40: =E38/E39 -> 1302.3509 | G40: 0.065 | H40: 2239.787 | I40: 1906.3734 | J40: 1722.3734 | K40: 1552.753

Sheet WACC
B5: Weighted Average Cost Of Capital
B6: All The Figures Are in INR Unless Stated Otherwise
B7: Peer Comps
G8: Debt/ | H8: Debt/ | I8: Levered | J8: Unlevered
B9: Name of the Company | C9: Country | D9: Total Debt | E9: Market Capitalisation | F9: Tax rate 1 | G9: Equity | H9: Capital | I9: Beta 2 | J9: Beta 3
B10: Infosys | C10: India | D10: 8737 | E10: 452250.12 | F10: 0.3 | G10: =D10/E10 -> 0.019318956 | H10: =D10/SUM(D10,E10) -> 0.018952807 | I10: 0.75 | J10: =I10/(1+(1-F10)*G10) -> 0.73999288
B11: TCS | C11: India | D11: 11283 | E11: 826588.33 | F11: 0.3 | G11: =D11/E11 -> 0.013650084 | H11: =D11/SUM(D11,E11) -> 0.013466268 | I11: 0.7 | J11: =I11/(1+(1-F11)*G11) -> 0.69337476
B12: HCL Technologies | C12: India | D12: 5215 | E12: 351962.37 | F12: 0.3 | G12: =D12/E12 -> 0.014816925 | H12: =D12/SUM(D12,E12) -> 0.014600589 | I12: 0.8 | J12: =I12/(1+(1-F12)*G12) -> 0.7917877
B13: Wipro | C13: India | D13: 20291 | E13: 177736.91 | F13: 0.3 | G13: =D13/E13 -> 0.11416312 | H13: =D13/SUM(D13,E13) -> 0.10246535 | I13: 0.85 | J13: =I13/(1+(1-F13)*G13) -> 0.78709958
E14: Average | F14: =AVERAGE(F10:F13) -> 0.3 | G14: =AVERAGE(G10:G13) -> 0.040487271 | H14: =AVERAGE(H10:H13) -> 0.037371255 | I14: =AVERAGE(I10:I13) -> 0.775 | J14: =AVERAGE(J10:J13) -> 0.75306373
E15: Median | F15: =MEDIAN(F10:F13) -> 0.3 | G15: =MEDIAN(G10:G13) -> 0.01706794 | H15: =MEDIAN(H10:H13) -> 0.016776698 | I15: =MEDIAN(I10:I13) -> 0.775 | J15: =MEDIAN(J10:J13) -> 0.76354623
B17: Cost of Debt | G17: Cost of Equity
B19: Pre tax cost of debt | E19: ='Data Sheet'!K27/'Data Sheet'!K59 -> 0.045335658 | G19: Riskfree rate | J19: 0.0676
B20: Tax rate | E20: 0.2727 | G20: Equity risk premium | J20: 0.062
B21: Post tax cost of debt | E21: =E19*(1-E20) -> 0.032972624 | G21: Levered beta 4 | J21: =E28 -> 0.78510519
G22: Cost of equity | J22: =J19+(J20*J21) -> 0.11627652
B23: Levered beta
G24: Cost of Debt
B25: Comps median unlevered beta | E25: =J15 -> 0.76354623 | I25: Current | J25: Target
B26: Target debt/equity | E26: =E30 -> 0.038822085 | G26: Total debt | H26: =D10 -> 8737 | I26: =H26/H28 -> 0.018952807 | J26: =H14 -> 0.037371255
B27: Tax rate | E27: =E20 -> 0.2727 | G27: Market Capitalization | H27: =E10 -> 452250.12 | I27: =H27/H28 -> 0.98104719 | J27: =J28-J26 -> 0.96262875
B28: Levered beta | E28: =E25*(1+(1-E27)*E26) -> 0.78510519 | G28: Total Capital | H28: =H26+H27 -> 460987.12 | I28: =H28/H28 -> 1 | J28: =I28 -> 1
B30: Debt/Equity | D30: =I26/I27 -> 0.019318956 | E30: =J26/J27 -> 0.038822085 | G30: Weighted average cost of capital
I31: Total cost | J31: Total weight
B32: Note: | G32: Debt | I32: =E21 -> 0.032972624 | J32: =J26 -> 0.037371255
B33: 1. Tax rate considered as marginal tax rate for country | G33: Equity | I33: =J22 -> 0.11627652 | J33: =J27 -> 0.96262875
B34: 2. Levered beta is based on 5 years monthly data | G34: Weighted average cost of capital | J34: =SUMPRODUCT(I32:I33,J32:J33) -> 0.11316335
B35: 3. Unlevered beta = levered beta/1+(1-tax rate)*debt/equity)
B36: 4. levered beta = unlevered beta*1+(1-tax rate)*debt/equity)

Sheet Football Field Anaylsis
B2: Football Field Analysis
J4: Data | K4: Data
L5: OpenLow | M5: Low | N5: OpenHigh | O5: High
K6: Comps | L6: ='Relative Valuation'!$L$24 -> 1204.1598 | M6: ='Relative Valuation'!$L$24 -> 1204.1598 | N6: ='Relative Valuation'!$N$24 -> 1436.8457 | O6: ='Relative Valuation'!$N$24 -> 1436.8457
K7: DCF Bear | L7: ='DCF Valuation Model'!$K$36 -> 1020.3737 | M7: ='DCF Valuation Model'!$K$36 -> 1020.3737 | N7: ='DCF Valuation Model'!$K$40 -> 1552.753 | O7: ='DCF Valuation Model'!$K$40 -> 1552.753
K8: DCF Base | L8: ='DCF Valuation Model'!$J$36 -> 1072.0237 | M8: ='DCF Valuation Model'!$J$36 -> 1072.0237 | N8: ='DCF Valuation Model'!$J$40 -> 1722.3734 | O8: ='DCF Valuation Model'!$J$40 -> 1722.3734
K9: DCF Bull | L9: ='DCF Valuation Model'!$H$36 -> 1199.0218 | M9: ='DCF Valuation Model'!$H$36 -> 1199.0218 | N9: ='DCF Valuation Model'!$H$40 -> 2239.787 | O9: ='DCF Valuation Model'!$H$40 -> 2239.787
K10: 52W H/L | L10: 982.4 | M10: 982.4 | N10: 1728 | O10: 1728

Sheet Financials>

Sheet Common Size Statement
B2: ="Common Size Income Statement"& "-" &'Data Sheet'!B1 -> Common Size Income Statement-INFOSYS LTD
B4: Particulars | C4: ='Data Sheet'!B16 -> 42825 | D4: ='Data Sheet'!C16 -> 43190 | E4: ='Data Sheet'!D16 -> 43555 | F4: ='Data Sheet'!E16 -> 43921 | G4: ='Data Sheet'!F16 -> 44286 | H4: ='Data Sheet'!G16 -> 44651 | I4: ='Data Sheet'!H16 -> 45016 | J4: ='Data Sheet'!I16 -> 45382 | ... L4: ='Data Sheet'!K16 -> 46112
B6: Sales | C6: =IFERROR('Data Sheet'!B17/'Data Sheet'!B$17,0) -> 1 | D6: =IFERROR('Data Sheet'!C17/'Data Sheet'!C$17,0) -> 1 | E6: =IFERROR('Data Sheet'!D17/'Data Sheet'!D$17,0) -> 1 | F6: =IFERROR('Data Sheet'!E17/'Data Sheet'!E$17,0) -> 1 | G6: =IFERROR('Data Sheet'!F17/'Data Sheet'!F$17,0) -> 1 | H6: =IFERROR('Data Sheet'!G17/'Data Sheet'!G$17,0) -> 1 | I6: =IFERROR('Data Sheet'!H17/'Data Sheet'!H$17,0) -> 1 | J6: =IFERROR('Data Sheet'!I17/'Data Sheet'!I$17,0) -> 1 | ... L6: =IFERROR('Data Sheet'!K17/'Data Sheet'!K$17,0) -> 1
B7: Raw Material Cost | C7: =IFERROR('Data Sheet'!B18/'Data Sheet'!B$17,0) -> 0 | D7: =IFERROR('Data Sheet'!C18/'Data Sheet'!C$17,0) -> 0 | E7: =IFERROR('Data Sheet'!D18/'Data Sheet'!D$17,0) -> 0 | F7: =IFERROR('Data Sheet'!E18/'Data Sheet'!E$17,0) -> 0 | G7: =IFERROR('Data Sheet'!F18/'Data Sheet'!F$17,0) -> 0 | H7: =IFERROR('Data Sheet'!G18/'Data Sheet'!G$17,0) -> 0 | I7: =IFERROR('Data Sheet'!H18/'Data Sheet'!H$17,0) -> 0 | J7: =IFERROR('Data Sheet'!I18/'Data Sheet'!I$17,0) -> 0 | ... L7: =IFERROR('Data Sheet'!K18/'Data Sheet'!K$17,0) -> 0
B8: Change in Inventory | C8: =IFERROR('Data Sheet'!B19/'Data Sheet'!B$17,0) -> 0 | D8: =IFERROR('Data Sheet'!C19/'Data Sheet'!C$17,0) -> 0 | E8: =IFERROR('Data Sheet'!D19/'Data Sheet'!D$17,0) -> 0 | F8: =IFERROR('Data Sheet'!E19/'Data Sheet'!E$17,0) -> 0 | G8: =IFERROR('Data Sheet'!F19/'Data Sheet'!F$17,0) -> 0 | H8: =IFERROR('Data Sheet'!G19/'Data Sheet'!G$17,0) -> 0 | I8: =IFERROR('Data Sheet'!H19/'Data Sheet'!H$17,0) -> 0 | J8: =IFERROR('Data Sheet'!I19/'Data Sheet'!I$17,0) -> 0 | ... L8: =IFERROR('Data Sheet'!K19/'Data Sheet'!K$17,0) -> 0
B9: Power and Fuel | C9: =IFERROR('Data Sheet'!B20/'Data Sheet'!B$17,0) -> 0.0033292448 | D9: =IFERROR('Data Sheet'!C20/'Data Sheet'!C$17,0) -> 0.0029352542 | E9: =IFERROR('Data Sheet'!D20/'Data Sheet'!D$17,0) -> 0.0026731176 | F9: =IFERROR('Data Sheet'!E20/'Data Sheet'!E$17,0) -> 0.0025222764 | G9: =IFERROR('Data Sheet'!F20/'Data Sheet'!F$17,0) -> 0.0014232821 | H9: =IFERROR('Data Sheet'!G20/'Data Sheet'!G$17,0) -> 0.0010851604 | I9: =IFERROR('Data Sheet'!H20/'Data Sheet'!H$17,0) -> 0.0011991797 | J9: =IFERROR('Data Sheet'!I20/'Data Sheet'!I$17,0) -> 0.0012949828 | ... L9: =IFERROR('Data Sheet'!K20/'Data Sheet'!K$17,0) -> 0.0012482508
B10: Other Mfr. Exp | C10: =IFERROR('Data Sheet'!B21/'Data Sheet'!B$17,0) -> 0.098008294 | D10: =IFERROR('Data Sheet'!C21/'Data Sheet'!C$17,0) -> 0.10331528 | E10: =IFERROR('Data Sheet'!D21/'Data Sheet'!D$17,0) -> 0.11977018 | F10: =IFERROR('Data Sheet'!E21/'Data Sheet'!E$17,0) -> 0.12210461 | G10: =IFERROR('Data Sheet'!F21/'Data Sheet'!F$17,0) -> 0.12739868 | H10: =IFERROR('Data Sheet'!G21/'Data Sheet'!G$17,0) -> 0.17009068 | I10: =IFERROR('Data Sheet'!H21/'Data Sheet'!H$17,0) -> 0.1794 | J10: =IFERROR('Data Sheet'!I21/'Data Sheet'!I$17,0) -> 0.17697013 | ... L10: =IFERROR('Data Sheet'!K21/'Data Sheet'!K$17,0) -> 0.18428212
B11: Employee Cost | C11: =IFERROR('Data Sheet'!B22/'Data Sheet'!B$17,0) -> 0.55004089 | D11: =IFERROR('Data Sheet'!C22/'Data Sheet'!C$17,0) -> 0.55162928 | E11: =IFERROR('Data Sheet'!D22/'Data Sheet'!D$17,0) -> 0.54820683 | F11: =IFERROR('Data Sheet'!E22/'Data Sheet'!E$17,0) -> 0.56057318 | G11: =IFERROR('Data Sheet'!F22/'Data Sheet'!F$17,0) -> 0.5528605 | H11: =IFERROR('Data Sheet'!G22/'Data Sheet'!G$17,0) -> 0.52611373 | I11: =IFERROR('Data Sheet'!H22/'Data Sheet'!H$17,0) -> 0.53400288 | J11: =IFERROR('Data Sheet'!I22/'Data Sheet'!I$17,0) -> 0.53774972 | ... L11: =IFERROR('Data Sheet'!K22/'Data Sheet'!K$17,0) -> 0.53239295
B12: Selling and admin | C12: =IFERROR('Data Sheet'!B23/'Data Sheet'!B$17,0) -> 0.066935343 | D12: =IFERROR('Data Sheet'!C23/'Data Sheet'!C$17,0) -> 0.065015173 | E12: =IFERROR('Data Sheet'!D23/'Data Sheet'!D$17,0) -> 0.067166616 | F12: =IFERROR('Data Sheet'!E23/'Data Sheet'!E$17,0) -> 0.059201903 | G12: =IFERROR('Data Sheet'!F23/'Data Sheet'!F$17,0) -> 0.031789951 | H12: =IFERROR('Data Sheet'!G23/'Data Sheet'!G$17,0) -> 0.035391028 | I12: =IFERROR('Data Sheet'!H23/'Data Sheet'!H$17,0) -> 0.03611166 | J12: =IFERROR('Data Sheet'!I23/'Data Sheet'!I$17,0) -> 0.037125008 | ... L12: =IFERROR('Data Sheet'!K23/'Data Sheet'!K$17,0) -> 0.037973692
B13: Other Expenses | C13: =IFERROR('Data Sheet'!B24/'Data Sheet'!B$17,0) -> 0.01003154 | D13: =IFERROR('Data Sheet'!C24/'Data Sheet'!C$17,0) -> 0.01020958 | E13: =IFERROR('Data Sheet'!D24/'Data Sheet'!D$17,0) -> 0.018215906 | F13: =IFERROR('Data Sheet'!E24/'Data Sheet'!E$17,0) -> 0.010342435 | G13: =IFERROR('Data Sheet'!F24/'Data Sheet'!F$17,0) -> 0.0089477665 | H13: =IFERROR('Data Sheet'!G24/'Data Sheet'!G$17,0) -> 0.0084346561 | I13: =IFERROR('Data Sheet'!H24/'Data Sheet'!H$17,0) -> 0.0099272997 | J13: =IFERROR('Data Sheet'!I24/'Data Sheet'!I$17,0) -> 0.0098262511 | ... L13: =IFERROR('Data Sheet'!K24/'Data Sheet'!K$17,0) -> 0.0074391268
B14: Other Income | C14: =IFERROR('Data Sheet'!B25/'Data Sheet'!B$17,0) -> 0.04453595 | D14: =IFERROR('Data Sheet'!C25/'Data Sheet'!C$17,0) -> 0.046949888 | E14: =IFERROR('Data Sheet'!D25/'Data Sheet'!D$17,0) -> 0.034859389 | F14: =IFERROR('Data Sheet'!E25/'Data Sheet'!E$17,0) -> 0.030873104 | G14: =IFERROR('Data Sheet'!F25/'Data Sheet'!F$17,0) -> 0.021906601 | H14: =IFERROR('Data Sheet'!G25/'Data Sheet'!G$17,0) -> 0.018866994 | I14: =IFERROR('Data Sheet'!H25/'Data Sheet'!H$17,0) -> 0.01840332 | J14: =IFERROR('Data Sheet'!I25/'Data Sheet'!I$17,0) -> 0.030656602 | ... L14: =IFERROR('Data Sheet'!K25/'Data Sheet'!K$17,0) -> 0.01697733
B15: Depreciation | C15: =IFERROR('Data Sheet'!B26/'Data Sheet'!B$17,0) -> 0.024867122 | D15: =IFERROR('Data Sheet'!C26/'Data Sheet'!C$17,0) -> 0.026417288 | E15: =IFERROR('Data Sheet'!D26/'Data Sheet'!D$17,0) -> 0.024324161 | F15: =IFERROR('Data Sheet'!E26/'Data Sheet'!E$17,0) -> 0.031864392 | G15: =IFERROR('Data Sheet'!F26/'Data Sheet'!F$17,0) -> 0.032516522 | H15: =IFERROR('Data Sheet'!G26/'Data Sheet'!G$17,0) -> 0.028575891 | I15: =IFERROR('Data Sheet'!H26/'Data Sheet'!H$17,0) -> 0.028787125 | J15: =IFERROR('Data Sheet'!I26/'Data Sheet'!I$17,0) -> 0.030441856 | ... L15: =IFERROR('Data Sheet'!K26/'Data Sheet'!K$17,0) -> 0.027439127
B16: Interest | C16: =IFERROR('Data Sheet'!B27/'Data Sheet'!B$17,0) -> 0 | D16: =IFERROR('Data Sheet'!C27/'Data Sheet'!C$17,0) -> 0 | E16: =IFERROR('Data Sheet'!D27/'Data Sheet'!D$17,0) -> 0 | F16: =IFERROR('Data Sheet'!E27/'Data Sheet'!E$17,0) -> 0.0018724323 | G16: =IFERROR('Data Sheet'!F27/'Data Sheet'!F$17,0) -> 0.0019408392 | H16: =IFERROR('Data Sheet'!G27/'Data Sheet'!G$17,0) -> 0.0016441825 | I16: =IFERROR('Data Sheet'!H27/'Data Sheet'!H$17,0) -> 0.0019350399 | J16: =IFERROR('Data Sheet'!I27/'Data Sheet'!I$17,0) -> 0.003058502 | ... L16: =IFERROR('Data Sheet'!K27/'Data Sheet'!K$17,0) -> 0.0023285754
B17: Profit before tax | C17: =IFERROR('Data Sheet'!B28/'Data Sheet'!B$17,0) -> 0.29132352 | D17: =IFERROR('Data Sheet'!C28/'Data Sheet'!C$17,0) -> 0.28742804 | E17: =IFERROR('Data Sheet'!D28/'Data Sheet'!D$17,0) -> 0.25450257 | F17: =IFERROR('Data Sheet'!E28/'Data Sheet'!E$17,0) -> 0.24239187 | G17: =IFERROR('Data Sheet'!F28/'Data Sheet'!F$17,0) -> 0.26502906 | H17: =IFERROR('Data Sheet'!G28/'Data Sheet'!G$17,0) -> 0.24753167 | I17: =IFERROR('Data Sheet'!H28/'Data Sheet'!H$17,0) -> 0.22704014 | J17: =IFERROR('Data Sheet'!I28/'Data Sheet'!I$17,0) -> 0.23419015 | ... L17: =IFERROR('Data Sheet'!K28/'Data Sheet'!K$17,0) -> 0.2238735
... B20: Dividend Amount | C20: =IFERROR('Data Sheet'!B31/'Data Sheet'!B$17,0) -> 0.086028853 | D20: =IFERROR('Data Sheet'!C31/'Data Sheet'!C$17,0) -> 0.13422194 | E20: =IFERROR('Data Sheet'!D31/'Data Sheet'!D$17,0) -> 0.11155125 | F20: =IFERROR('Data Sheet'!E31/'Data Sheet'!E$17,0) -> 0.081803262 | G20: =IFERROR('Data Sheet'!F31/'Data Sheet'!F$17,0) -> 0.11415718 | H20: =IFERROR('Data Sheet'!G31/'Data Sheet'!G$17,0) -> 0.10693434 | I20: =IFERROR('Data Sheet'!H31/'Data Sheet'!H$17,0) -> 0.095860786 | J20: =IFERROR('Data Sheet'!I31/'Data Sheet'!I$17,0) -> 0.12398777 | ... L20: =IFERROR('Data Sheet'!K31/'Data Sheet'!K$17,0) -> 0.10876238
B23: ="Common Size Balance Sheet"&"-"&'Data Sheet'!B1 -> Common Size Balance Sheet-INFOSYS LTD
B25: Particulars | C25: ='Data Sheet'!B16 -> 42825 | D25: ='Data Sheet'!C16 -> 43190 | E25: ='Data Sheet'!D16 -> 43555 | F25: ='Data Sheet'!E16 -> 43921 | G25: ='Data Sheet'!F16 -> 44286 | H25: ='Data Sheet'!G16 -> 44651 | I25: ='Data Sheet'!H16 -> 45016 | J25: ='Data Sheet'!I16 -> 45382 | ... L25: ='Data Sheet'!K16 -> 46112
B27: Equity Share Capital | C27: ='Historical FS'!C39/'Historical FS'!C$43 -> 0.013758599 | D27: ='Historical FS'!D39/'Historical FS'!D$43 -> 0.013711578 | E27: ='Historical FS'!E39/'Historical FS'!E$43 -> 0.025813052 | F27: ='Historical FS'!F39/'Historical FS'!F$43 -> 0.023115468 | G27: ='Historical FS'!G39/'Historical FS'!G$43 -> 0.019756118 | H27: ='Historical FS'!H39/'Historical FS'!H$43 -> 0.017973254 | I27: ='Historical FS'!I39/'Historical FS'!I$43 -> 0.01660567 | J27: ='Historical FS'!J39/'Historical FS'!J$43 -> 0.015225702 | ... L27: ='Historical FS'!L39/'Historical FS'!L$43 -> 0.013118324
B28: Reserves | C28: ='Historical FS'!C40/'Historical FS'!C$43 -> 0.8158705 | D28: ='Historical FS'!D40/'Historical FS'!D$43 -> 0.80448399 | E28: ='Historical FS'!E40/'Historical FS'!E$43 -> 0.74677039 | F28: ='Historical FS'!F40/'Historical FS'!F$43 -> 0.68984749 | G28: ='Historical FS'!G40/'Historical FS'!G$43 -> 0.69041307 | H28: ='Historical FS'!H40/'Historical FS'!H$43 -> 0.627539 | I28: ='Historical FS'!I40/'Historical FS'!I$43 -> 0.58860638 | J28: ='Historical FS'!J40/'Historical FS'!J$43 -> 0.6325908 | ... L28: ='Historical FS'!L40/'Historical FS'!L$43 -> 0.58869128
B29: Borrowings | C29: ='Historical FS'!C41/'Historical FS'!C$43 -> 0 | D29: ='Historical FS'!D41/'Historical FS'!D$43 -> 0 | E29: ='Historical FS'!E41/'Historical FS'!E$43 -> 0 | F29: ='Historical FS'!F41/'Historical FS'!F$43 -> 0.05046841 | G29: ='Historical FS'!G41/'Historical FS'!G$43 -> 0.049529816 | H29: ='Historical FS'!H41/'Historical FS'!H$43 -> 0.046894945 | I29: ='Historical FS'!I41/'Historical FS'!I$43 -> 0.066607275 | J29: ='Historical FS'!J41/'Historical FS'!J$43 -> 0.061454198 | ... L29: ='Historical FS'!L41/'Historical FS'!L$43 -> 0.059473193
B30: Other Liabilities | C30: ='Historical FS'!C42/'Historical FS'!C$43 -> 0.1703709 | D30: ='Historical FS'!D42/'Historical FS'!D$43 -> 0.18180443 | E30: ='Historical FS'!E42/'Historical FS'!E$43 -> 0.22741655 | F30: ='Historical FS'!F42/'Historical FS'!F$43 -> 0.23656863 | G30: ='Historical FS'!G42/'Historical FS'!G$43 -> 0.24030099 | H30: ='Historical FS'!H42/'Historical FS'!H$43 -> 0.3075928 | I30: ='Historical FS'!I42/'Historical FS'!I$43 -> 0.32818068 | J30: ='Historical FS'!J42/'Historical FS'!J$43 -> 0.2907293 | ... L30: ='Historical FS'!L42/'Historical FS'!L$43 -> 0.3387172
B31: Total liablities | C31: ='Historical FS'!C43/'Historical FS'!C$43 -> 1 | D31: ='Historical FS'!D43/'Historical FS'!D$43 -> 1 | E31: ='Historical FS'!E43/'Historical FS'!E$43 -> 1 | F31: ='Historical FS'!F43/'Historical FS'!F$43 -> 1 | G31: ='Historical FS'!G43/'Historical FS'!G$43 -> 1 | H31: ='Historical FS'!H43/'Historical FS'!H$43 -> 1 | I31: ='Historical FS'!I43/'Historical FS'!I$43 -> 1 | J31: ='Historical FS'!J43/'Historical FS'!J$43 -> 1 | ... L31: ='Historical FS'!L43/'Historical FS'!L$43 -> 1
B33: Fixed Assests Net Block | C33: ='Historical FS'!C45/'Historical FS'!C$56 -> 0.17052725 | D33: ='Historical FS'!D45/'Historical FS'!D$56 -> 0.1584645 | E33: ='Historical FS'!E45/'Historical FS'!E$56 -> 0.18687698 | F33: ='Historical FS'!F45/'Historical FS'!F$56 -> 0.25913943 | G33: ='Historical FS'!G45/'Historical FS'!G$56 -> 0.23723154 | H33: ='Historical FS'!H45/'Historical FS'!H$56 -> 0.22102477 | I33: ='Historical FS'!I45/'Historical FS'!I$56 -> 0.23455809 | J33: ='Historical FS'!J45/'Historical FS'!J$56 -> 0.20307308 | ... L33: ='Historical FS'!L45/'Historical FS'!L$56 -> 0.21887639
B34: Capital Work in Progress | C34: ='Historical FS'!C46/'Historical FS'!C$56 -> 0.01641651 | D34: ='Historical FS'!D46/'Historical FS'!D$56 -> 0.020239701 | E34: ='Historical FS'!E46/'Historical FS'!E$56 -> 0.016510837 | F34: ='Historical FS'!F46/'Historical FS'!F$56 -> 0.010392157 | G34: ='Historical FS'!G46/'Historical FS'!G$56 -> 0.0085758667 | H34: ='Historical FS'!H46/'Historical FS'!H$56 -> 0.0035638102 | I34: ='Historical FS'!I46/'Historical FS'!I$56 -> 0.0023114707 | J34: ='Historical FS'!J46/'Historical FS'!J$56 -> 0.002154095 | ... L34: ='Historical FS'!L46/'Historical FS'!L$56 -> 0.0034092088
B35: Investments | C35: ='Historical FS'!C47/'Historical FS'!C$56 -> 0.19751527 | D35: ='Historical FS'!D47/'Historical FS'!D$56 -> 0.15328486 | E35: ='Historical FS'!E47/'Historical FS'!E$56 -> 0.13395427 | F35: ='Historical FS'!F47/'Historical FS'!F$56 -> 0.09577342 | G35: ='Historical FS'!G47/'Historical FS'!G$56 -> 0.13212602 | H35: ='Historical FS'!H47/'Historical FS'!H$56 -> 0.17411269 | I35: ='Historical FS'!I47/'Historical FS'!I$56 -> 0.15632926 | J35: ='Historical FS'!J47/'Historical FS'!J$56 -> 0.18102485 | ... L35: ='Historical FS'!L47/'Historical FS'!L$56 -> 0.14181271
B36: Other Assets | C36: ='Historical FS'!C48/'Historical FS'!C$56 -> 0.19524222 | D36: ='Historical FS'!D48/'Historical FS'!D$56 -> 0.25263078 | E36: ='Historical FS'!E48/'Historical FS'!E$56 -> 0.2535151 | F36: ='Historical FS'!F48/'Historical FS'!F$56 -> 0.2301634 | G36: ='Historical FS'!G48/'Historical FS'!G$56 -> 0.21273172 | H36: ='Historical FS'!H48/'Historical FS'!H$56 -> 0.25716831 | I36: ='Historical FS'!I48/'Historical FS'!I$56 -> 0.30504992 | J36: ='Historical FS'!J48/'Historical FS'!J$56 -> 0.28306867 | ... L36: ='Historical FS'!L48/'Historical FS'!L$56 -> 0.26364332
B37: Total Non Current Assets | C37: ='Historical FS'!C49/'Historical FS'!C$56 -> 0.57970126 | D37: ='Historical FS'!D49/'Historical FS'!D$56 -> 0.58461984 | E37: ='Historical FS'!E49/'Historical FS'!E$56 -> 0.59085718 | F37: ='Historical FS'!F49/'Historical FS'!F$56 -> 0.59546841 | G37: ='Historical FS'!G49/'Historical FS'!G$56 -> 0.59066514 | H37: ='Historical FS'!H49/'Historical FS'!H$56 -> 0.65586958 | I37: ='Historical FS'!I49/'Historical FS'!I$56 -> 0.69824874 | J37: ='Historical FS'!J49/'Historical FS'!J$56 -> 0.66932069 | ... L37: ='Historical FS'!L49/'Historical FS'!L$56 -> 0.62774163
B39: Receivables | C39: ='Historical FS'!C51/'Historical FS'!C$56 -> 0.14819358 | D39: ='Historical FS'!D51/'Historical FS'!D$56 -> 0.16562276 | E39: ='Historical FS'!E51/'Historical FS'!E$56 -> 0.17637333 | F39: ='Historical FS'!F51/'Historical FS'!F$56 -> 0.20138344 | G39: ='Historical FS'!G51/'Historical FS'!G$56 -> 0.17946071 | H39: ='Historical FS'!H51/'Historical FS'!H$56 -> 0.19445039 | I39: ='Historical FS'!I51/'Historical FS'!I$56 -> 0.20405149 | J39: ='Historical FS'!J51/'Historical FS'!J$56 -> 0.22197471 | ... L39: ='Historical FS'!L51/'Historical FS'!L$56 -> 0.22836514
B40: Inventory | C40: ='Historical FS'!C52/'Historical FS'!C$56 -> 0 | D40: ='Historical FS'!D52/'Historical FS'!D$56 -> 0 | E40: ='Historical FS'!E52/'Historical FS'!E$56 -> 0 | F40: ='Historical FS'!F52/'Historical FS'!F$56 -> 0 | G40: ='Historical FS'!G52/'Historical FS'!G$56 -> 0 | H40: ='Historical FS'!H52/'Historical FS'!H$56 -> 0 | I40: ='Historical FS'!I52/'Historical FS'!I$56 -> 0 | J40: ='Historical FS'!J52/'Historical FS'!J$56 -> 0 | ... L40: ='Historical FS'!L52/'Historical FS'!L$56 -> 0
B41: Cash & Bank | C41: ='Historical FS'!C53/'Historical FS'!C$56 -> 0.27210516 | D41: ='Historical FS'!D53/'Historical FS'!D$56 -> 0.2497574 | E41: ='Historical FS'!E53/'Historical FS'!E$56 -> 0.23276949 | F41: ='Historical FS'!F53/'Historical FS'!F$56 -> 0.20314815 | G41: ='Historical FS'!G53/'Historical FS'!G$56 -> 0.22987415 | H41: ='Historical FS'!H53/'Historical FS'!H$56 -> 0.14968003 | I41: ='Historical FS'!I53/'Historical FS'!I$56 -> 0.097699766 | J41: ='Historical FS'!J53/'Historical FS'!J$56 -> 0.1087046 | ... L41: ='Historical FS'!L53/'Historical FS'!L$56 -> 0.14389324
B42: Total Current Assets | C42: ='Historical FS'!C54/'Historical FS'!C$56 -> 0.42029874 | D42: ='Historical FS'!D54/'Historical FS'!D$56 -> 0.41538016 | E42: ='Historical FS'!E54/'Historical FS'!E$56 -> 0.40914282 | F42: ='Historical FS'!F54/'Historical FS'!F$56 -> 0.40453159 | G42: ='Historical FS'!G54/'Historical FS'!G$56 -> 0.40933486 | H42: ='Historical FS'!H54/'Historical FS'!H$56 -> 0.34413042 | I42: ='Historical FS'!I54/'Historical FS'!I$56 -> 0.30175126 | J42: ='Historical FS'!J54/'Historical FS'!J$56 -> 0.33067931 | ... L42: ='Historical FS'!L54/'Historical FS'!L$56 -> 0.37225837
B44: Total Assets | C44: ='Historical FS'!C56/'Historical FS'!C$56 -> 1 | D44: ='Historical FS'!D56/'Historical FS'!D$56 -> 1 | E44: ='Historical FS'!E56/'Historical FS'!E$56 -> 1 | F44: ='Historical FS'!F56/'Historical FS'!F$56 -> 1 | G44: ='Historical FS'!G56/'Historical FS'!G$56 -> 1 | H44: ='Historical FS'!H56/'Historical FS'!H$56 -> 1 | I44: ='Historical FS'!I56/'Historical FS'!I$56 -> 1 | J44: ='Historical FS'!J56/'Historical FS'!J$56 -> 1 | ... L44: ='Historical FS'!L56/'Historical FS'!L$56 -> 1

Sheet Ratio analysis
B2: ="Ratio Analysis -"&'Data Sheet'!B1 -> Ratio Analysis -INFOSYS LTD
B3: Years | C3: ='Data Sheet'!B16 -> 42825 | D3: ='Data Sheet'!C16 -> 43190 | E3: ='Data Sheet'!D16 -> 43555 | F3: ='Data Sheet'!E16 -> 43921 | G3: ='Data Sheet'!F16 -> 44286 | H3: ='Data Sheet'!G16 -> 44651 | I3: ='Data Sheet'!H16 -> 45016 | J3: ='Data Sheet'!I16 -> 45382 | ... L3: ='Data Sheet'!K16 -> 46112 | M3: Trendlines | N3: Mean | O3: Median
B5: Sales growth | D5: =IFERROR('Historical FS'!D6/'Historical FS'!C6-1,0) -> 0.029758776 | E5: =IFERROR('Historical FS'!E6/'Historical FS'!D6-1,0) -> 0.1723292 | F5: =IFERROR('Historical FS'!F6/'Historical FS'!E6-1,0) -> 0.098167523 | G5: =IFERROR('Historical FS'!G6/'Historical FS'!F6-1,0) -> 0.10662951 | H5: =IFERROR('Historical FS'!H6/'Historical FS'!G6-1,0) -> 0.21069552 | I5: =IFERROR('Historical FS'!I6/'Historical FS'!H6-1,0) -> 0.20655864 | J5: =IFERROR('Historical FS'!J6/'Historical FS'!I6-1,0) -> 0.047033734 | K5: =IFERROR('Historical FS'!K6/'Historical FS'!J6-1,0) -> 0.060649444 | L5: =IFERROR('Historical FS'!L6/'Historical FS'!K6-1,0) -> 0.096079514 | N5: =IFERROR(AVERAGE(D5:L5),0) -> 0.11421132 | O5: =IFERROR(MEDIAN(D5:L5),0) -> 0.098167523
B6: EBITDA growth | D6: =IFERROR('Historical FS'!D14/'Historical FS'!C14-1,0) -> 0.01171791 | E6: =IFERROR('Historical FS'!E14/'Historical FS'!D14-1,0) -> 0.071618319 | F6: =IFERROR('Historical FS'!F14/'Historical FS'!E14-1,0) -> 0.10396629 | G6: =IFERROR('Historical FS'!G14/'Historical FS'!F14-1,0) -> 0.25248125 | H6: =IFERROR('Historical FS'!H14/'Historical FS'!G14-1,0) -> 0.12915486 | I6: =IFERROR('Historical FS'!I14/'Historical FS'!H14-1,0) -> 0.11555683 | J6: =IFERROR('Historical FS'!J14/'Historical FS'!I14-1,0) -> 0.03686308 | K6: =IFERROR('Historical FS'!K14/'Historical FS'!J14-1,0) -> 0.077172272 | L6: =IFERROR('Historical FS'!L14/'Historical FS'!K14-1,0) -> 0.077581813 | N6: =IFERROR(AVERAGE(D6:L6),0) -> 0.097345847 | O6: =IFERROR(MEDIAN(D6:L6),0) -> 0.077581813
B7: EBT growth | D7: =IFERROR('Historical FS'!D22/'Historical FS'!C22-1,0) -> 0.015989173 | E7: =IFERROR('Historical FS'!E22/'Historical FS'!D22-1,0) -> 0.038036507 | F7: =IFERROR('Historical FS'!F22/'Historical FS'!E22-1,0) -> 0.045910365 | G7: =IFERROR('Historical FS'!G22/'Historical FS'!F22-1,0) -> 0.20997864 | H7: =IFERROR('Historical FS'!H22/'Historical FS'!G22-1,0) -> 0.13076461 | I7: =IFERROR('Historical FS'!I22/'Historical FS'!H22-1,0) -> 0.10667552 | J7: =IFERROR('Historical FS'!J22/'Historical FS'!I22-1,0) -> 0.080007202 | K7: =IFERROR('Historical FS'!K22/'Historical FS'!J22-1,0) -> 0.045015005 | L7: =IFERROR('Historical FS'!L22/'Historical FS'!K22-1,0) -> 0.063470538 | N7: =IFERROR(AVERAGE(D7:L7),0) -> 0.081760841 | O7: =IFERROR(MEDIAN(D7:L7),0) -> 0.063470538
B8: Net profit growth | D8: =IFERROR('Historical FS'!D26/'Historical FS'!C26-1,0) -> 0.11677001 | E8: =IFERROR('Historical FS'!E26/'Historical FS'!D26-1,0) -> -0.038617506 | F8: =IFERROR('Historical FS'!F26/'Historical FS'!E26-1,0) -> 0.079753407 | G8: =IFERROR('Historical FS'!G26/'Historical FS'!F26-1,0) -> 0.16731775 | H8: =IFERROR('Historical FS'!H26/'Historical FS'!G26-1,0) -> 0.14019461 | I8: =IFERROR('Historical FS'!I26/'Historical FS'!H26-1,0) -> 0.088593877 | J8: =IFERROR('Historical FS'!J26/'Historical FS'!I26-1,0) -> 0.088767214 | K8: =IFERROR('Historical FS'!K26/'Historical FS'!J26-1,0) -> 0.019125267 | L8: =IFERROR('Historical FS'!L26/'Historical FS'!K26-1,0) -> 0.10183178 | N8: =IFERROR(AVERAGE(D8:L8),0) -> 0.084859601 | O8: =IFERROR(MEDIAN(D8:L8),0) -> 0.088767214
B9: Dividend growth | D9: =IFERROR('Historical FS'!D33/'Historical FS'!C33-1,0) -> 0.68963897 | E9: =IFERROR('Historical FS'!E33/'Historical FS'!D33-1,0) -> -0.02583858 | F9: =IFERROR('Historical FS'!F33/'Historical FS'!E33-1,0) -> -0.17390646 | G9: =IFERROR('Historical FS'!G33/'Historical FS'!F33-1,0) -> 0.54369512 | H9: =IFERROR('Historical FS'!H33/'Historical FS'!G33-1,0) -> 0.14865158 | I9: =IFERROR('Historical FS'!I33/'Historical FS'!H33-1,0) -> 0.096761529 | J9: =IFERROR('Historical FS'!J33/'Historical FS'!I33-1,0) -> 0.35349861 | K9: =IFERROR('Historical FS'!K33/'Historical FS'!J33-1,0) -> -0.064855345 | L9: =IFERROR('Historical FS'!L33/'Historical FS'!K33-1,0) -> 0.116149 | N9: =IFERROR(AVERAGE(D9:L9),0) -> 0.18708827 | O9: =IFERROR(MEDIAN(D9:L9),0) -> 0.116149
B11: Gross margin | C11: =IFERROR('Historical FS'!C11,0) -> 0.34862158 | D11: =IFERROR('Historical FS'!D11,0) -> 0.34212019 | E11: =IFERROR('Historical FS'!E11,0) -> 0.32934986 | F11: =IFERROR('Historical FS'!F11,0) -> 0.31479993 | G11: =IFERROR('Historical FS'!G11,0) -> 0.31831754 | H11: =IFERROR('Historical FS'!H11,0) -> 0.30271043 | I11: =IFERROR('Historical FS'!I11,0) -> 0.28539794 | J11: =IFERROR('Historical FS'!J11,0) -> 0.28398516 | ... L11: =IFERROR('Historical FS'!L11,0) -> 0.28207669 | N11: =IFERROR(AVERAGE(D11:L11),0) -> 0.30482983 | O11: =IFERROR(MEDIAN(D11:L11),0) -> 0.30271043
B12: EBITDA margin | C12: =IFERROR('Historical FS'!C15,0) -> 0.27165469 | D12: =IFERROR('Historical FS'!D15,0) -> 0.26689544 | E12: =IFERROR('Historical FS'!E15,0) -> 0.24396734 | F12: =IFERROR('Historical FS'!F15,0) -> 0.24525559 | G12: =IFERROR('Historical FS'!G15,0) -> 0.27757982 | H12: =IFERROR('Historical FS'!H15,0) -> 0.25888475 | I12: =IFERROR('Historical FS'!I15,0) -> 0.23935898 | J12: =IFERROR('Historical FS'!J15,0) -> 0.2370339 | ... L12: =IFERROR('Historical FS'!L15,0) -> 0.23666387 | N12: =IFERROR(AVERAGE(D12:L12),0) -> 0.24959624 | O12: =IFERROR(MEDIAN(D12:L12),0) -> 0.24396734
B13: EBIT margin | C13: =IFERROR(('Historical FS'!C14-'Historical FS'!C18)/'Historical FS'!C6,) -> 0.24678757 | D13: =IFERROR(('Historical FS'!D14-'Historical FS'!D18)/'Historical FS'!D6,) -> 0.24047815 | E13: =IFERROR(('Historical FS'!E14-'Historical FS'!E18)/'Historical FS'!E6,) -> 0.21964318 | F13: =IFERROR(('Historical FS'!F14-'Historical FS'!F18)/'Historical FS'!F6,) -> 0.2133912 | G13: =IFERROR(('Historical FS'!G14-'Historical FS'!G18)/'Historical FS'!G6,) -> 0.2450633 | H13: =IFERROR(('Historical FS'!H14-'Historical FS'!H18)/'Historical FS'!H6,) -> 0.23030886 | I13: =IFERROR(('Historical FS'!I14-'Historical FS'!I18)/'Historical FS'!I6,) -> 0.21057186 | J13: =IFERROR(('Historical FS'!J14-'Historical FS'!J18)/'Historical FS'!J6,) -> 0.20659205 | ... L13: =IFERROR(('Historical FS'!L14-'Historical FS'!L18)/'Historical FS'!L6,) -> 0.20922474 | N13: =IFERROR(AVERAGE(D13:L13),0) -> 0.22071961 | O13: =IFERROR(MEDIAN(D13:L13),0) -> 0.2133912
B14: EBT margin | C14: =IFERROR('Historical FS'!C23,0) -> 0.29132352 | D14: =IFERROR('Historical FS'!D23,0) -> 0.28742804 | E14: =IFERROR('Historical FS'!E23,0) -> 0.25450257 | F14: =IFERROR('Historical FS'!F23,0) -> 0.24239187 | G14: =IFERROR('Historical FS'!G23,0) -> 0.26502906 | H14: =IFERROR('Historical FS'!H23,0) -> 0.24753167 | I14: =IFERROR('Historical FS'!I23,0) -> 0.22704014 | J14: =IFERROR('Historical FS'!J23,0) -> 0.23419015 | ... L14: =IFERROR('Historical FS'!L23,0) -> 0.2238735 | N14: =IFERROR(AVERAGE(D14:L14),0) -> 0.24585834 | O14: =IFERROR(MEDIAN(D14:L14),0) -> 0.24239187
B15: Net profit margin | C15: =IFERROR('Historical FS'!C27,0) -> 0.2095818 | D15: =IFERROR('Historical FS'!D27,0) -> 0.22729077 | E15: =IFERROR('Historical FS'!E27,0) -> 0.1863925 | F15: =IFERROR('Historical FS'!F27,0) -> 0.18326706 | G15: =IFERROR('Historical FS'!G27,0) -> 0.19331754 | H15: =IFERROR('Historical FS'!H27,0) -> 0.18206033 | I15: =IFERROR('Historical FS'!I27,0) -> 0.16426036 | J15: =IFERROR('Historical FS'!J27,0) -> 0.17080757 | ... L15: =IFERROR('Historical FS'!L27,0) -> 0.16498181 | N15: =IFERROR(AVERAGE(D15:L15),0) -> 0.18183316 | O15: =IFERROR(MEDIAN(D15:L15),0) -> 0.18206033
B17: Sales expense% sales | C17: =IFERROR('Historical FS'!C12/'Historical FS'!C6,0) -> 0.076966883 | D17: =IFERROR('Historical FS'!D12/'Historical FS'!D6,0) -> 0.075224753 | E17: =IFERROR('Historical FS'!E12/'Historical FS'!E6,0) -> 0.085382522 | F17: =IFERROR('Historical FS'!F12/'Historical FS'!F6,0) -> 0.069544338 | G17: =IFERROR('Historical FS'!G12/'Historical FS'!G6,0) -> 0.040737718 | H17: =IFERROR('Historical FS'!H12/'Historical FS'!H6,0) -> 0.043825684 | I17: =IFERROR('Historical FS'!I12/'Historical FS'!I6,0) -> 0.04603896 | J17: =IFERROR('Historical FS'!J12/'Historical FS'!J6,0) -> 0.046951259 | ... L17: =IFERROR('Historical FS'!L12/'Historical FS'!L6,0) -> 0.045412818 | N17: =IFERROR(AVERAGE(D17:L17),0) -> 0.055233594 | O17: =IFERROR(MEDIAN(D17:L17),0) -> 0.04603896
B18: Depreciation% sales | C18: =IFERROR('Historical FS'!C19,0) -> 0.024867122 | D18: =IFERROR('Historical FS'!D19,0) -> 0.026417288 | E18: =IFERROR('Historical FS'!E19,0) -> 0.024324161 | F18: =IFERROR('Historical FS'!F19,0) -> 0.031864392 | G18: =IFERROR('Historical FS'!G19,0) -> 0.032516522 | H18: =IFERROR('Historical FS'!H19,0) -> 0.028575891 | I18: =IFERROR('Historical FS'!I19,0) -> 0.028787125 | J18: =IFERROR('Historical FS'!J19,0) -> 0.030441856 | ... L18: =IFERROR('Historical FS'!L19,0) -> 0.027439127 | N18: =IFERROR(AVERAGE(D18:L18),0) -> 0.028876627 | O18: =IFERROR(MEDIAN(D18:L18),0) -> 0.028787125
B19: Operating income% sales | C19: =IFERROR('Ratio analysis'!C13,0) -> 0.24678757 | D19: =IFERROR('Ratio analysis'!D13,0) -> 0.24047815 | E19: =IFERROR('Ratio analysis'!E13,0) -> 0.21964318 | F19: =IFERROR('Ratio analysis'!F13,0) -> 0.2133912 | G19: =IFERROR('Ratio analysis'!G13,0) -> 0.2450633 | H19: =IFERROR('Ratio analysis'!H13,0) -> 0.23030886 | I19: =IFERROR('Ratio analysis'!I13,0) -> 0.21057186 | J19: =IFERROR('Ratio analysis'!J13,0) -> 0.20659205 | ... L19: =IFERROR('Ratio analysis'!L13,0) -> 0.20922474 | N19: =IFERROR(AVERAGE(D19:L19),0) -> 0.22071961 | O19: =IFERROR(MEDIAN(D19:L19),0) -> 0.2133912
B21: Return on capital employed | C21: =IFERROR(('Historical FS'!C14-'Historical FS'!C18)/SUM('Historical FS'!C39:C41),0) -> 0.24500594 | D21: =IFERROR(('Historical FS'!D14-'Historical FS'!D18)/SUM('Historical FS'!D39:D41),0) -> 0.26121713 | E21: =IFERROR(('Historical FS'!E14-'Historical FS'!E18)/SUM('Historical FS'!E39:E41),0) -> 0.27959291 | F21: =IFERROR(('Historical FS'!F14-'Historical FS'!F18)/SUM('Historical FS'!F39:F41),0) -> 0.27644365 | G21: =IFERROR(('Historical FS'!G14-'Historical FS'!G18)/SUM('Historical FS'!G39:G41),0) -> 0.30145943 | H21: =IFERROR(('Historical FS'!H14-'Historical FS'!H18)/SUM('Historical FS'!H39:H41),0) -> 0.34661734 | I21: =IFERROR(('Historical FS'!I14-'Historical FS'!I18)/SUM('Historical FS'!I39:I41),0) -> 0.3692089 | J21: =IFERROR(('Historical FS'!J14-'Historical FS'!J18)/SUM('Historical FS'!J39:J41),0) -> 0.32906971 | ... L21: =IFERROR(('Historical FS'!L14-'Historical FS'!L18)/SUM('Historical FS'!L39:L41),0) -> 0.36635041 | N21: =IFERROR(AVERAGE(D21:L21),0) -> 0.31786848 | O21: =IFERROR(MEDIAN(D21:L21),0) -> 0.32906971
B22: Retained earning | C22: =IFERROR('Historical FS'!C35,0) -> 0.58952135 | D22: =IFERROR('Historical FS'!D35,0) -> 0.40947034 | E22: =IFERROR('Historical FS'!E35,0) -> 0.40152498 | F22: =IFERROR('Historical FS'!F35,0) -> 0.55363904 | G22: =IFERROR('Historical FS'!G35,0) -> 0.4094836 | H22: =IFERROR('Historical FS'!H35,0) -> 0.41264337 | I22: =IFERROR('Historical FS'!I35,0) -> 0.41640949 | J22: =IFERROR('Historical FS'!J35,0) -> 0.2741085 | ... L22: =IFERROR('Historical FS'!L35,0) -> 0.34076135 | N22: =IFERROR(AVERAGE(D22:L22),0) -> 0.3946201 | O22: =IFERROR(MEDIAN(D22:L22),0) -> 0.40947034
B23: Return on equity% | C23: =IFERROR('Historical FS'!C26/SUM('Historical FS'!C39:C40),) -> 0.20806877 | D23: =IFERROR('Historical FS'!D26/SUM('Historical FS'!D39:D40),) -> 0.24689247 | E23: =IFERROR('Historical FS'!E26/SUM('Historical FS'!E39:E40),) -> 0.23726674 | F23: =IFERROR('Historical FS'!F26/SUM('Historical FS'!F39:F40),) -> 0.2542246 | G23: =IFERROR('Historical FS'!G26/SUM('Historical FS'!G39:G40),) -> 0.25439091 | H23: =IFERROR('Historical FS'!H26/SUM('Historical FS'!H39:H40),) -> 0.29390843 | I23: =IFERROR('Historical FS'!I26/SUM('Historical FS'!I39:I40),) -> 0.31970507 | J23: =IFERROR('Historical FS'!J26/SUM('Historical FS'!J39:J40),) -> 0.29788007 | ... L23: =IFERROR('Historical FS'!L26/SUM('Historical FS'!L39:L40),) -> 0.31742989 | N23: =IFERROR(AVERAGE(D23:L23),0) -> 0.27787481 | O23: =IFERROR(MEDIAN(D23:L23),0) -> 0.2791751
B24: Self sustained growth rate | C24: =C22*C23 -> 0.12266098 | D24: =D22*D23 -> 0.10109514 | E24: =E22*E23 -> 0.095268523 | F24: =F22*F23 -> 0.14074866 | G24: =G22*G23 -> 0.1041689 | H24: =H22*H23 -> 0.12127936 | I24: =I22*I23 -> 0.13312822 | J24: =J22*J23 -> 0.081651459 | ... L24: =L22*L23 -> 0.10816784 | N24: =IFERROR(AVERAGE(D24:L24),0) -> 0.10873603 | O24: =IFERROR(MEDIAN(D24:L24),0) -> 0.1041689
B25: Interest coverage ratio | C25: =IFERROR(('Historical FS'!C14-'Historical FS'!C18)/'Historical FS'!C20,0) -> 0 | D25: =IFERROR(('Historical FS'!D14-'Historical FS'!D18)/'Historical FS'!D20,0) -> 0 | E25: =IFERROR(('Historical FS'!E14-'Historical FS'!E18)/'Historical FS'!E20,0) -> 0 | F25: =IFERROR(('Historical FS'!F14-'Historical FS'!F18)/'Historical FS'!F20,0) -> 113.96471 | G25: =IFERROR(('Historical FS'!G14-'Historical FS'!G18)/'Historical FS'!G20,0) -> 126.26667 | H25: =IFERROR(('Historical FS'!H14-'Historical FS'!H18)/'Historical FS'!H20,0) -> 140.075 | I25: =IFERROR(('Historical FS'!I14-'Historical FS'!I18)/'Historical FS'!I20,0) -> 108.82042 | J25: =IFERROR(('Historical FS'!J14-'Historical FS'!J18)/'Historical FS'!J20,0) -> 67.546809 | ... L25: =IFERROR(('Historical FS'!L14-'Historical FS'!L18)/'Historical FS'!L20,0) -> 89.850962 | N25: =IFERROR(AVERAGE(D25:L25),0) -> 81.030507 | O25: =IFERROR(MEDIAN(D25:L25),0) -> 89.850962
B27: Debtor turnover ratio | C27: =IFERROR('Historical FS'!C6/'Historical FS'!C51,0) -> 5.557864 | D27: =IFERROR('Historical FS'!D6/'Historical FS'!D51,0) -> 5.3661543 | E27: =IFERROR('Historical FS'!E6/'Historical FS'!E51,0) -> 5.5759763 | F27: =IFERROR('Historical FS'!F6/'Historical FS'!F51,0) -> 4.9110726 | G27: =IFERROR('Historical FS'!G6/'Historical FS'!G51,0) -> 5.207422 | H27: =IFERROR('Historical FS'!H6/'Historical FS'!H51,0) -> 5.3591065 | I27: =IFERROR('Historical FS'!I6/'Historical FS'!I51,0) -> 5.7727738 | J27: =IFERROR('Historical FS'!J6/'Historical FS'!J51,0) -> 5.0895903 | ... L27: =IFERROR('Historical FS'!L6/'Historical FS'!L51,0) -> 5.0703866 | N27: =IFERROR(AVERAGE(D27:L27),0) -> 5.2870625 | O27: =IFERROR(MEDIAN(D27:L27),0) -> 5.2310803
B28: Creditor turnover ratio | C28: =IFERROR('Historical FS'!C6/'Historical FS'!C41,0) -> 0 | D28: =IFERROR('Historical FS'!D6/'Historical FS'!D41,0) -> 0 | E28: =IFERROR('Historical FS'!E6/'Historical FS'!E41,0) -> 0 | F28: =IFERROR('Historical FS'!F6/'Historical FS'!F41,0) -> 19.59659 | G28: =IFERROR('Historical FS'!G6/'Historical FS'!G41,0) -> 18.867981 | H28: =IFERROR('Historical FS'!H6/'Historical FS'!H41,0) -> 22.221593 | I28: =IFERROR('Historical FS'!I6/'Historical FS'!I41,0) -> 17.684902 | J28: =IFERROR('Historical FS'!J6/'Historical FS'!J41,0) -> 18.383778 | ... L28: =IFERROR('Historical FS'!L6/'Historical FS'!L41,0) -> 19.469268 | N28: =IFERROR(AVERAGE(D28:L28),0) -> 15.115079 | O28: =IFERROR(MEDIAN(D28:L28),0) -> 18.867981
B29: Inventory turnover ratio | C29: =IFERROR('Historical FS'!C6/'Historical FS'!C52,0) -> 0 | D29: =IFERROR('Historical FS'!D6/'Historical FS'!D52,0) -> 0 | E29: =IFERROR('Historical FS'!E6/'Historical FS'!E52,0) -> 0 | F29: =IFERROR('Historical FS'!F6/'Historical FS'!F52,0) -> 0 | G29: =IFERROR('Historical FS'!G6/'Historical FS'!G52,0) -> 0 | H29: =IFERROR('Historical FS'!H6/'Historical FS'!H52,0) -> 0 | I29: =IFERROR('Historical FS'!I6/'Historical FS'!I52,0) -> 0 | J29: =IFERROR('Historical FS'!J6/'Historical FS'!J52,0) -> 0 | ... L29: =IFERROR('Historical FS'!L6/'Historical FS'!L52,0) -> 0 | N29: =IFERROR(AVERAGE(D29:L29),0) -> 0 | O29: =IFERROR(MEDIAN(D29:L29),0) -> 0
B30: Fixed asset turnover ratio | C30: =IFERROR('Historical FS'!C6/'Historical FS'!C45,0) -> 4.8299598 | D30: =IFERROR('Historical FS'!D6/'Historical FS'!D45,0) -> 5.6085573 | E30: =IFERROR('Historical FS'!E6/'Historical FS'!E45,0) -> 5.2625716 | F30: =IFERROR('Historical FS'!F6/'Historical FS'!F45,0) -> 3.8165118 | G30: =IFERROR('Historical FS'!G6/'Historical FS'!G45,0) -> 3.939306 | H30: =IFERROR('Historical FS'!H6/'Historical FS'!H45,0) -> 4.7147674 | I30: =IFERROR('Historical FS'!I6/'Historical FS'!I45,0) -> 5.0219675 | J30: =IFERROR('Historical FS'!J6/'Historical FS'!J45,0) -> 5.5633191 | ... L30: =IFERROR('Historical FS'!L6/'Historical FS'!L45,0) -> 5.2901984 | N30: =IFERROR(AVERAGE(D30:L30),0) -> 4.942396 | O30: =IFERROR(MEDIAN(D30:L30),0) -> 5.2625716
B31: Capital turnover ratio | C31: =IFERROR('Historical FS'!C6/SUM('Historical FS'!C39:C40),0) -> 0.99278073 | D31: =IFERROR('Historical FS'!D6/SUM('Historical FS'!D39:D40),0) -> 1.0862406 | E31: =IFERROR('Historical FS'!E6/SUM('Historical FS'!E39:E40),0) -> 1.2729414 | F31: =IFERROR('Historical FS'!F6/SUM('Historical FS'!F39:F40),0) -> 1.3871811 | G31: =IFERROR('Historical FS'!G6/SUM('Historical FS'!G39:G40),0) -> 1.3159225 | H31: =IFERROR('Historical FS'!H6/SUM('Historical FS'!H39:H40),0) -> 1.6143464 | I31: =IFERROR('Historical FS'!I6/SUM('Historical FS'!I39:I40),0) -> 1.9463312 | J31: =IFERROR('Historical FS'!J6/SUM('Historical FS'!J39:J40),0) -> 1.7439512 | ... L31: =IFERROR('Historical FS'!L6/SUM('Historical FS'!L39:L40),0) -> 1.9240296 | N31: =IFERROR(AVERAGE(D31:L31),0) -> 1.5546646 | O31: =IFERROR(MEDIAN(D31:L31),0) -> 1.6143464
B33: Debtor days | C33: =IFERROR(365/C27,0) -> 65.672712 | D33: =IFERROR(365/D27,0) -> 68.018916 | E33: =IFERROR(365/E27,0) -> 65.459389 | F33: =IFERROR(365/F27,0) -> 74.321849 | G33: =IFERROR(365/G27,0) -> 70.092265 | H33: =IFERROR(365/H27,0) -> 68.108368 | I33: =IFERROR(365/I27,0) -> 63.227837 | J33: =IFERROR(365/J27,0) -> 71.715006 | ... L33: =IFERROR(365/L27,0) -> 71.986622 | N33: =IFERROR(AVERAGE(D33:L33),0) -> 69.189502 | O33: =IFERROR(MEDIAN(D33:L33),0) -> 69.775262
B34: Payable days | C34: =IFERROR(365/C28,0) -> 0 | D34: =IFERROR(365/D28,0) -> 0 | E34: =IFERROR(365/E28,0) -> 0 | F34: =IFERROR(365/F28,0) -> 18.62569 | G34: =IFERROR(365/G28,0) -> 19.344942 | H34: =IFERROR(365/H28,0) -> 16.425465 | I34: =IFERROR(365/I28,0) -> 20.639074 | J34: =IFERROR(365/J28,0) -> 19.854461 | ... L34: =IFERROR(365/L28,0) -> 18.747495 | N34: =IFERROR(AVERAGE(D34:L34),0) -> 14.673409 | O34: =IFERROR(MEDIAN(D34:L34),0) -> 18.62569
B35: Inventory days | C35: =IFERROR(365/C29,0) -> 0 | D35: =IFERROR(365/D29,0) -> 0 | E35: =IFERROR(365/E29,0) -> 0 | F35: =IFERROR(365/F29,0) -> 0 | G35: =IFERROR(365/G29,0) -> 0 | H35: =IFERROR(365/H29,0) -> 0 | I35: =IFERROR(365/I29,0) -> 0 | J35: =IFERROR(365/J29,0) -> 0 | ... L35: =IFERROR(365/L29,0) -> 0 | N35: =IFERROR(AVERAGE(D35:L35),0) -> 0 | O35: =IFERROR(MEDIAN(D35:L35),0) -> 0
B36: Cash conversion | C36: =SUM(C33,C35)-C34 -> 65.672712 | D36: =SUM(D33,D35)-D34 -> 68.018916 | E36: =SUM(E33,E35)-E34 -> 65.459389 | F36: =SUM(F33,F35)-F34 -> 55.696159 | G36: =SUM(G33,G35)-G34 -> 50.747323 | H36: =SUM(H33,H35)-H34 -> 51.682903 | I36: =SUM(I33,I35)-I34 -> 42.588763 | J36: =SUM(J33,J35)-J34 -> 51.860545 | ... L36: =SUM(L33,L35)-L34 -> 53.239127 | N36: =IFERROR(AVERAGE(D36:L36),0) -> 54.516093 | O36: =IFERROR(MEDIAN(D36:L36),0) -> 51.860545
B38: CFO/sales | C38: =IFERROR('Historical FS'!C62/'Historical FS'!C6,0) -> 0.16837509 | D38: =IFERROR('Historical FS'!D62/'Historical FS'!D6,0) -> 0.18743087 | E38: =IFERROR('Historical FS'!E62/'Historical FS'!E6,0) -> 0.17951013 | F38: =IFERROR('Historical FS'!F62/'Historical FS'!F6,0) -> 0.18727627 | G38: =IFERROR('Historical FS'!G62/'Historical FS'!G6,0) -> 0.23114898 | H38: =IFERROR('Historical FS'!H62/'Historical FS'!H6,0) -> 0.19635649 | I38: =IFERROR('Historical FS'!I62/'Historical FS'!I6,0) -> 0.15307937 | J38: =IFERROR('Historical FS'!J62/'Historical FS'!J6,0) -> 0.16405284 | ... L38: =IFERROR('Historical FS'!L62/'Historical FS'!L6,0) -> 0.1902379 | N38: =IFERROR(AVERAGE(D38:L38),0) -> 0.18978754 | O38: =IFERROR(MEDIAN(D38:L38),0) -> 0.18743087
B39: CFO/total assets | C39: =IFERROR('Historical FS'!C62/'Historical FS'!C56,0) -> 0.13868043 | D39: =IFERROR('Historical FS'!D62/'Historical FS'!D56,0) -> 0.16658055 | E39: =IFERROR('Historical FS'!E62/'Historical FS'!E56,0) -> 0.17653986 | F39: =IFERROR('Historical FS'!F62/'Historical FS'!F56,0) -> 0.18521786 | G39: =IFERROR('Historical FS'!G62/'Historical FS'!G56,0) -> 0.21601511 | H39: =IFERROR('Historical FS'!H62/'Historical FS'!H56,0) -> 0.20461925 | I39: =IFERROR('Historical FS'!I62/'Historical FS'!I56,0) -> 0.18031879 | J39: =IFERROR('Historical FS'!J62/'Historical FS'!J56,0) -> 0.18534039 | ... L39: =IFERROR('Historical FS'!L62/'Historical FS'!L56,0) -> 0.22027637 | N39: =IFERROR(AVERAGE(D39:L39),0) -> 0.19737982 | O39: =IFERROR(MEDIAN(D39:L39),0) -> 0.18534039
B40: CFO/total debt | C40: =IFERROR('Historical FS'!C62/'Historical FS'!C41,0) -> 0 | D40: =IFERROR('Historical FS'!D62/'Historical FS'!D41,0) -> 0 | E40: =IFERROR('Historical FS'!E62/'Historical FS'!E41,0) -> 0 | F40: =IFERROR('Historical FS'!F62/'Historical FS'!F41,0) -> 3.6699763 | G40: =IFERROR('Historical FS'!G62/'Historical FS'!G41,0) -> 4.3613146 | H40: =IFERROR('Historical FS'!H62/'Historical FS'!H41,0) -> 4.363354 | I40: =IFERROR('Historical FS'!I62/'Historical FS'!I41,0) -> 2.7071936 | J40: =IFERROR('Historical FS'!J62/'Historical FS'!J41,0) -> 3.015911 | ... L40: =IFERROR('Historical FS'!L62/'Historical FS'!L41,0) -> 3.7037925 | N40: =IFERROR(AVERAGE(D40:L40),0) -> 2.906687 | O40: =IFERROR(MEDIAN(D40:L40),0) -> 3.6699763

Sheet Data Room>

Sheet Historical FS
B2: ="Historical Financial Statement -"&'Data Sheet'!B1 -> Historical Financial Statement -INFOSYS LTD
B3: Years | C3: ='Data Sheet'!B16 -> 42825 | D3: ='Data Sheet'!C16 -> 43190 | E3: ='Data Sheet'!D16 -> 43555 | F3: ='Data Sheet'!E16 -> 43921 | G3: ='Data Sheet'!F16 -> 44286 | H3: ='Data Sheet'!G16 -> 44651 | I3: ='Data Sheet'!H16 -> 45016 | J3: ='Data Sheet'!I16 -> 45382 | ... L3: ='Data Sheet'!K16 -> 46112
A5: # | B5: Income Statement
B6: Sales | C6: =IFERROR('Data Sheet'!B17,0) -> 68484 | D6: =IFERROR('Data Sheet'!C17,0) -> 70522 | E6: =IFERROR('Data Sheet'!D17,0) -> 82675 | F6: =IFERROR('Data Sheet'!E17,0) -> 90791 | G6: =IFERROR('Data Sheet'!F17,0) -> 100472 | H6: =IFERROR('Data Sheet'!G17,0) -> 121641 | I6: =IFERROR('Data Sheet'!H17,0) -> 146767 | J6: =IFERROR('Data Sheet'!I17,0) -> 153670 | ... L6: =IFERROR('Data Sheet'!K17,0) -> 178650
B7: Sales Growth Rate | C7: 0 | D7: =(D6/C6-1) -> 0.029758776 | E7: =(E6/D6-1) -> 0.1723292 | F7: =(F6/E6-1) -> 0.098167523 | G7: =(G6/F6-1) -> 0.10662951 | H7: =(H6/G6-1) -> 0.21069552 | I7: =(I6/H6-1) -> 0.20655864 | J7: =(J6/I6-1) -> 0.047033734 | K7: =(K6/J6-1) -> 0.060649444 | L7: =(L6/K6-1) -> 0.096079514
B8: COGS | C8: =IFERROR(SUM('Data Sheet'!B20:B22,'Data Sheet'!B18)-1*'Data Sheet'!B19,0) -> 44609 | D8: =IFERROR(SUM('Data Sheet'!C20:C22,'Data Sheet'!C18)-1*'Data Sheet'!C19,0) -> 46395 | E8: =IFERROR(SUM('Data Sheet'!D20:D22,'Data Sheet'!D18)-1*'Data Sheet'!D19,0) -> 55446 | F8: =IFERROR(SUM('Data Sheet'!E20:E22,'Data Sheet'!E18)-1*'Data Sheet'!E19,0) -> 62210 | G8: =IFERROR(SUM('Data Sheet'!F20:F22,'Data Sheet'!F18)-1*'Data Sheet'!F19,0) -> 68490 | H8: =IFERROR(SUM('Data Sheet'!G20:G22,'Data Sheet'!G18)-1*'Data Sheet'!G19,0) -> 84819 | I8: =IFERROR(SUM('Data Sheet'!H20:H22,'Data Sheet'!H18)-1*'Data Sheet'!H19,0) -> 104880 | J8: =IFERROR(SUM('Data Sheet'!I20:I22,'Data Sheet'!I18)-1*'Data Sheet'!I19,0) -> 110030 | ... L8: =IFERROR(SUM('Data Sheet'!K20:K22,'Data Sheet'!K18)-1*'Data Sheet'!K19,0) -> 128257
B9: COGS% of Sales | C9: =(C8/C6) -> 0.65137842 | D9: =(D8/D6) -> 0.65787981 | E9: =(E8/E6) -> 0.67065014 | F9: =(F8/F6) -> 0.68520007 | G9: =(G8/G6) -> 0.68168246 | H9: =(H8/H6) -> 0.69728957 | I9: =(I8/I6) -> 0.71460206 | J9: =(J8/J6) -> 0.71601484 | ... L9: =(L8/L6) -> 0.71792331
B10: Gross Profits | C10: =(C6-C8) -> 23875 | D10: =(D6-D8) -> 24127 | E10: =(E6-E8) -> 27229 | F10: =(F6-F8) -> 28581 | G10: =(G6-G8) -> 31982 | H10: =(H6-H8) -> 36822 | I10: =(I6-I8) -> 41887 | J10: =(J6-J8) -> 43640 | ... L10: =(L6-L8) -> 50393
B11: Gross Profits% of Sales | C11: =C10/C6 -> 0.34862158 | D11: =D10/D6 -> 0.34212019 | E11: =E10/E6 -> 0.32934986 | F11: =F10/F6 -> 0.31479993 | G11: =G10/G6 -> 0.31831754 | H11: =H10/H6 -> 0.30271043 | I11: =I10/I6 -> 0.28539794 | J11: =J10/J6 -> 0.28398516 | ... L11: =L10/L6 -> 0.28207669
B12: Selling & Adm Expense | C12: =IFERROR(SUM('Data Sheet'!B23:B24),0) -> 5271 | D12: =IFERROR(SUM('Data Sheet'!C23:C24),0) -> 5305 | E12: =IFERROR(SUM('Data Sheet'!D23:D24),0) -> 7059 | F12: =IFERROR(SUM('Data Sheet'!E23:E24),0) -> 6314 | G12: =IFERROR(SUM('Data Sheet'!F23:F24),0) -> 4093 | H12: =IFERROR(SUM('Data Sheet'!G23:G24),0) -> 5331 | I12: =IFERROR(SUM('Data Sheet'!H23:H24),0) -> 6757 | J12: =IFERROR(SUM('Data Sheet'!I23:I24),0) -> 7215 | ... L12: =IFERROR(SUM('Data Sheet'!K23:K24),0) -> 8113
B13: S&A Exp % of sales | C13: =C12/C6 -> 0.076966883 | D13: =D12/D6 -> 0.075224753 | E13: =E12/E6 -> 0.085382522 | F13: =F12/F6 -> 0.069544338 | G13: =G12/G6 -> 0.040737718 | H13: =H12/H6 -> 0.043825684 | I13: =I12/I6 -> 0.04603896 | J13: =J12/J6 -> 0.046951259 | ... L13: =L12/L6 -> 0.045412818
B14: EBITDA | C14: =C10-C12 -> 18604 | D14: =D10-D12 -> 18822 | E14: =E10-E12 -> 20170 | F14: =F10-F12 -> 22267 | G14: =G10-G12 -> 27889 | H14: =H10-H12 -> 31491 | I14: =I10-I12 -> 35130 | J14: =J10-J12 -> 36425 | ... L14: =L10-L12 -> 42280
B15: EBITDA% of Sales | C15: =C14/C6 -> 0.27165469 | D15: =D14/D6 -> 0.26689544 | E15: =E14/E6 -> 0.24396734 | F15: =F14/F6 -> 0.24525559 | G15: =G14/G6 -> 0.27757982 | H15: =H14/H6 -> 0.25888475 | I15: =I14/I6 -> 0.23935898 | J15: =J14/J6 -> 0.2370339 | ... L15: =L14/L6 -> 0.23666387
B16: Other Income | C16: =IFERROR('Data Sheet'!B25,0) -> 3050 | D16: =IFERROR('Data Sheet'!C25,0) -> 3311 | E16: =IFERROR('Data Sheet'!D25,0) -> 2882 | F16: =IFERROR('Data Sheet'!E25,0) -> 2803 | G16: =IFERROR('Data Sheet'!F25,0) -> 2201 | H16: =IFERROR('Data Sheet'!G25,0) -> 2295 | I16: =IFERROR('Data Sheet'!H25,0) -> 2701 | J16: =IFERROR('Data Sheet'!I25,0) -> 4711 | ... L16: =IFERROR('Data Sheet'!K25,0) -> 3033
B17: % of Sales | C17: =C16/C6 -> 0.04453595 | D17: =D16/D6 -> 0.046949888 | E17: =E16/E6 -> 0.034859389 | F17: =F16/F6 -> 0.030873104 | G17: =G16/G6 -> 0.021906601 | H17: =H16/H6 -> 0.018866994 | I17: =I16/I6 -> 0.01840332 | J17: =J16/J6 -> 0.030656602 | ... L17: =L16/L6 -> 0.01697733
B18: Depreciation | C18: =IFERROR('Data Sheet'!B26,0) -> 1703 | D18: =IFERROR('Data Sheet'!C26,0) -> 1863 | E18: =IFERROR('Data Sheet'!D26,0) -> 2011 | F18: =IFERROR('Data Sheet'!E26,0) -> 2893 | G18: =IFERROR('Data Sheet'!F26,0) -> 3267 | H18: =IFERROR('Data Sheet'!G26,0) -> 3476 | I18: =IFERROR('Data Sheet'!H26,0) -> 4225 | J18: =IFERROR('Data Sheet'!I26,0) -> 4678 | ... L18: =IFERROR('Data Sheet'!K26,0) -> 4902
B19: Depreciation% of Sales | C19: =C18/C6 -> 0.024867122 | D19: =D18/D6 -> 0.026417288 | E19: =E18/E6 -> 0.024324161 | F19: =F18/F6 -> 0.031864392 | G19: =G18/G6 -> 0.032516522 | H19: =H18/H6 -> 0.028575891 | I19: =I18/I6 -> 0.028787125 | J19: =J18/J6 -> 0.030441856 | ... L19: =L18/L6 -> 0.027439127
B20: Interest | C20: =IFERROR('Data Sheet'!B27,0) -> 0 | D20: =IFERROR('Data Sheet'!C27,0) -> 0 | E20: =IFERROR('Data Sheet'!D27,0) -> 0 | F20: =IFERROR('Data Sheet'!E27,0) -> 170 | G20: =IFERROR('Data Sheet'!F27,0) -> 195 | H20: =IFERROR('Data Sheet'!G27,0) -> 200 | I20: =IFERROR('Data Sheet'!H27,0) -> 284 | J20: =IFERROR('Data Sheet'!I27,0) -> 470 | ... L20: =IFERROR('Data Sheet'!K27,0) -> 416
B21: Interest% of Sales | C21: =C20/C6 -> 0 | D21: =D20/D6 -> 0 | E21: =E20/E6 -> 0 | F21: =F20/F6 -> 0.0018724323 | G21: =G20/G6 -> 0.0019408392 | H21: =H20/H6 -> 0.0016441825 | I21: =I20/I6 -> 0.0019350399 | J21: =J20/J6 -> 0.003058502 | ... L21: =L20/L6 -> 0.0023285754
B22: EBT | C22: =C14+C16-(C18+C20) -> 19951 | D22: =D14+D16-(D18+D20) -> 20270 | E22: =E14+E16-(E18+E20) -> 21041 | F22: =F14+F16-(F18+F20) -> 22007 | G22: =G14+G16-(G18+G20) -> 26628 | H22: =H14+H16-(H18+H20) -> 30110 | I22: =I14+I16-(I18+I20) -> 33322 | J22: =J14+J16-(J18+J20) -> 35988 | ... L22: =L14+L16-(L18+L20) -> 39995
B23: EBT% of Sales | C23: =C22/C6 -> 0.29132352 | D23: =D22/D6 -> 0.28742804 | E23: =E22/E6 -> 0.25450257 | F23: =F22/F6 -> 0.24239187 | G23: =G22/G6 -> 0.26502906 | H23: =H22/H6 -> 0.24753167 | I23: =I22/I6 -> 0.22704014 | J23: =J22/J6 -> 0.23419015 | ... L23: =L22/L6 -> 0.2238735
B24: Tax | C24: =IFERROR('Data Sheet'!B29,0) -> 5598 | D24: =IFERROR('Data Sheet'!C29,0) -> 4241 | E24: =IFERROR('Data Sheet'!D29,0) -> 5631 | F24: =IFERROR('Data Sheet'!E29,0) -> 5368 | G24: =IFERROR('Data Sheet'!F29,0) -> 7205 | H24: =IFERROR('Data Sheet'!G29,0) -> 7964 | I24: =IFERROR('Data Sheet'!H29,0) -> 9214 | J24: =IFERROR('Data Sheet'!I29,0) -> 9740 | ... L24: =IFERROR('Data Sheet'!K29,0) -> 10521
B25: Effective Tax Rate | C25: =C24/C22 -> 0.28058744 | D25: =D24/D22 -> 0.20922546 | E25: =E24/E22 -> 0.26762036 | F25: =F24/F22 -> 0.24392239 | G25: =G24/G22 -> 0.27057984 | H25: =H24/H22 -> 0.26449684 | I25: =I24/I22 -> 0.27651401 | J25: =J24/J22 -> 0.27064577 | ... L25: =L24/L22 -> 0.26305788
B26: Net Profits | C26: =C22-C24 -> 14353 | D26: =D22-D24 -> 16029 | E26: =E22-E24 -> 15410 | F26: =F22-F24 -> 16639 | G26: =G22-G24 -> 19423 | H26: =H22-H24 -> 22146 | I26: =I22-I24 -> 24108 | J26: =J22-J24 -> 26248 | ... L26: =L22-L24 -> 29474
B27: Net Margins | C27: =C26/C6 -> 0.2095818 | D27: =D26/D6 -> 0.22729077 | E27: =E26/E6 -> 0.1863925 | F27: =F26/F6 -> 0.18326706 | G27: =G26/G6 -> 0.19331754 | H27: =H26/H6 -> 0.18206033 | I27: =I26/I6 -> 0.16426036 | J27: =J26/J6 -> 0.17080757 | ... L27: =L26/L6 -> 0.16498181
B29: No. of Equity Shares | C29: =IFERROR('Data Sheet'!B93,0) -> 459.39 | D29: =IFERROR('Data Sheet'!C93,0) -> 436.82 | E29: =IFERROR('Data Sheet'!D93,0) -> 436.89 | F29: =IFERROR('Data Sheet'!E93,0) -> 425.9 | G29: =IFERROR('Data Sheet'!F93,0) -> 426.07 | H29: =IFERROR('Data Sheet'!G93,0) -> 420.67 | I29: =IFERROR('Data Sheet'!H93,0) -> 414.86 | J29: =IFERROR('Data Sheet'!I93,0) -> 415.09 | ... L29: =IFERROR('Data Sheet'!K93,0) -> 405.56
B31: Earning Per Share | C31: =C26/C29 -> 31.243606 | D31: =D26/D29 -> 36.694748 | E31: =E26/E29 -> 35.272036 | F31: =F26/F29 -> 39.067856 | G31: =G26/G29 -> 45.586406 | H31: =H26/H29 -> 52.644591 | I31: =I26/I29 -> 58.11117 | J31: =J26/J29 -> 63.234479 | ... L31: =L26/L29 -> 72.67482
B32: EPS Growth rate | D32: =IFERROR(C31/D31,0) -> 0.85144624 | E32: =IFERROR(D31/E31,0) -> 1.0403354 | F32: =IFERROR(E31/F31,0) -> 0.90284033 | G32: =IFERROR(F31/G31,0) -> 0.85700672 | H32: =IFERROR(G31/H31,0) -> 0.86592764 | I32: =IFERROR(H31/I31,0) -> 0.90592894 | J32: =IFERROR(I31/J31,0) -> 0.91897918 | K32: =IFERROR(J31/K31,0) -> 0.98180098 | L32: =IFERROR(K31/L31,0) -> 0.88623015
B33: Dividend Per Share | C33: =IFERROR('Data Sheet'!B31/'Historical FS'!C29,0) -> 12.824833 | D33: =IFERROR('Data Sheet'!C31/'Historical FS'!D29,0) -> 21.669337 | E33: =IFERROR('Data Sheet'!D31/'Historical FS'!E29,0) -> 21.109433 | F33: =IFERROR('Data Sheet'!E31/'Historical FS'!F29,0) -> 17.438366 | G33: =IFERROR('Data Sheet'!F31/'Historical FS'!G29,0) -> 26.91952 | H33: =IFERROR('Data Sheet'!G31/'Historical FS'!H29,0) -> 30.92115 | I33: =IFERROR('Data Sheet'!H31/'Historical FS'!I29,0) -> 33.913127 | J33: =IFERROR('Data Sheet'!I31/'Historical FS'!J29,0) -> 45.901371 | ... L33: =IFERROR('Data Sheet'!K31/'Historical FS'!L29,0) -> 47.91005
B34: Dividend Payout Ratio | C34: =IFERROR(C33/C31,0) -> 0.41047865 | D34: =IFERROR(D33/D31,0) -> 0.59052966 | E34: =IFERROR(E33/E31,0) -> 0.59847502 | F34: =IFERROR(F33/F31,0) -> 0.44636096 | G34: =IFERROR(G33/G31,0) -> 0.5905164 | H34: =IFERROR(H33/H31,0) -> 0.58735663 | I34: =IFERROR(I33/I31,0) -> 0.58359051 | J34: =IFERROR(J33/J31,0) -> 0.7258915 | ... L34: =IFERROR(L33/L31,0) -> 0.65923865
B35: Retained Earning | C35: =IFERROR(IF(C31>C33,1-C34,0),0) -> 0.58952135 | D35: =IFERROR(IF(D31>D33,1-D34,0),0) -> 0.40947034 | E35: =IFERROR(IF(E31>E33,1-E34,0),0) -> 0.40152498 | F35: =IFERROR(IF(F31>F33,1-F34,0),0) -> 0.55363904 | G35: =IFERROR(IF(G31>G33,1-G34,0),0) -> 0.4094836 | H35: =IFERROR(IF(H31>H33,1-H34,0),0) -> 0.41264337 | I35: =IFERROR(IF(I31>I33,1-I34,0),0) -> 0.41640949 | J35: =IFERROR(IF(J31>J33,1-J34,0),0) -> 0.2741085 | ... L35: =IFERROR(IF(L31>L33,1-L34,0),0) -> 0.34076135
A38: # | B38: Balance Sheet
B39: Equity Share Capital | C39: =IFERROR('Data Sheet'!B57,0) -> 1144 | D39: =IFERROR('Data Sheet'!C57,0) -> 1088 | E39: =IFERROR('Data Sheet'!D57,0) -> 2170 | F39: =IFERROR('Data Sheet'!E57,0) -> 2122 | G39: =IFERROR('Data Sheet'!F57,0) -> 2124 | H39: =IFERROR('Data Sheet'!G57,0) -> 2098 | I39: =IFERROR('Data Sheet'!H57,0) -> 2069 | J39: =IFERROR('Data Sheet'!I57,0) -> 2071 | ... L39: =IFERROR('Data Sheet'!K57,0) -> 2024
B40: Reserves | C40: =IFERROR('Data Sheet'!B58,0) -> 67838 | D40: =IFERROR('Data Sheet'!C58,0) -> 63835 | E40: =IFERROR('Data Sheet'!D58,0) -> 62778 | F40: =IFERROR('Data Sheet'!E58,0) -> 63328 | G40: =IFERROR('Data Sheet'!F58,0) -> 74227 | H40: =IFERROR('Data Sheet'!G58,0) -> 73252 | I40: =IFERROR('Data Sheet'!H58,0) -> 73338 | J40: =IFERROR('Data Sheet'!I58,0) -> 86045 | ... L40: =IFERROR('Data Sheet'!K58,0) -> 90828
B41: Borrowings | C41: =IFERROR('Data Sheet'!B59,0) -> 0 | D41: =IFERROR('Data Sheet'!C59,0) -> 0 | E41: =IFERROR('Data Sheet'!D59,0) -> 0 | F41: =IFERROR('Data Sheet'!E59,0) -> 4633 | G41: =IFERROR('Data Sheet'!F59,0) -> 5325 | H41: =IFERROR('Data Sheet'!G59,0) -> 5474 | I41: =IFERROR('Data Sheet'!H59,0) -> 8299 | J41: =IFERROR('Data Sheet'!I59,0) -> 8359 | ... L41: =IFERROR('Data Sheet'!K59,0) -> 9176
B42: Other Liabilities | C42: =IFERROR('Data Sheet'!B60,0) -> 14166 | D42: =IFERROR('Data Sheet'!C60,0) -> 14426 | E42: =IFERROR('Data Sheet'!D60,0) -> 19118 | F42: =IFERROR('Data Sheet'!E60,0) -> 21717 | G42: =IFERROR('Data Sheet'!F60,0) -> 25835 | H42: =IFERROR('Data Sheet'!G60,0) -> 35905 | I42: =IFERROR('Data Sheet'!H60,0) -> 40890 | J42: =IFERROR('Data Sheet'!I60,0) -> 39545 | ... L42: =IFERROR('Data Sheet'!K60,0) -> 52260
B43: Total liablities | C43: =IFERROR('Data Sheet'!B61,0) -> 83148 | D43: =IFERROR('Data Sheet'!C61,0) -> 79349 | E43: =IFERROR('Data Sheet'!D61,0) -> 84066 | F43: =IFERROR('Data Sheet'!E61,0) -> 91800 | G43: =IFERROR('Data Sheet'!F61,0) -> 107511 | H43: =IFERROR('Data Sheet'!G61,0) -> 116729 | I43: =IFERROR('Data Sheet'!H61,0) -> 124596 | J43: =IFERROR('Data Sheet'!I61,0) -> 136020 | ... L43: =IFERROR('Data Sheet'!K61,0) -> 154288
B45: Fixed Assests Net Block | C45: =IFERROR('Data Sheet'!B62,0) -> 14179 | D45: =IFERROR('Data Sheet'!C62,0) -> 12574 | E45: =IFERROR('Data Sheet'!D62,0) -> 15710 | F45: =IFERROR('Data Sheet'!E62,0) -> 23789 | G45: =IFERROR('Data Sheet'!F62,0) -> 25505 | H45: =IFERROR('Data Sheet'!G62,0) -> 25800 | I45: =IFERROR('Data Sheet'!H62,0) -> 29225 | J45: =IFERROR('Data Sheet'!I62,0) -> 27622 | ... L45: =IFERROR('Data Sheet'!K62,0) -> 33770
B46: Capital Work in Progress | C46: =IFERROR('Data Sheet'!B63,0) -> 1365 | D46: =IFERROR('Data Sheet'!C63,0) -> 1606 | E46: =IFERROR('Data Sheet'!D63,0) -> 1388 | F46: =IFERROR('Data Sheet'!E63,0) -> 954 | G46: =IFERROR('Data Sheet'!F63,0) -> 922 | H46: =IFERROR('Data Sheet'!G63,0) -> 416 | I46: =IFERROR('Data Sheet'!H63,0) -> 288 | J46: =IFERROR('Data Sheet'!I63,0) -> 293 | ... L46: =IFERROR('Data Sheet'!K63,0) -> 526
B47: Investments | C47: =IFERROR('Data Sheet'!B64,0) -> 16423 | D47: =IFERROR('Data Sheet'!C64,0) -> 12163 | E47: =IFERROR('Data Sheet'!D64,0) -> 11261 | F47: =IFERROR('Data Sheet'!E64,0) -> 8792 | G47: =IFERROR('Data Sheet'!F64,0) -> 14205 | H47: =IFERROR('Data Sheet'!G64,0) -> 20324 | I47: =IFERROR('Data Sheet'!H64,0) -> 19478 | J47: =IFERROR('Data Sheet'!I64,0) -> 24623 | ... L47: =IFERROR('Data Sheet'!K64,0) -> 21880
B48: Other Assets | C48: =IFERROR('Data Sheet'!B65-SUM('Data Sheet'!B67:B69,0),0) -> 16234 | D48: =IFERROR('Data Sheet'!C65-SUM('Data Sheet'!C67:C69,0),0) -> 20046 | E48: =IFERROR('Data Sheet'!D65-SUM('Data Sheet'!D67:D69,0),0) -> 21312 | F48: =IFERROR('Data Sheet'!E65-SUM('Data Sheet'!E67:E69,0),0) -> 21129 | G48: =IFERROR('Data Sheet'!F65-SUM('Data Sheet'!F67:F69,0),0) -> 22871 | H48: =IFERROR('Data Sheet'!G65-SUM('Data Sheet'!G67:G69,0),0) -> 30019 | I48: =IFERROR('Data Sheet'!H65-SUM('Data Sheet'!H67:H69,0),0) -> 38008 | J48: =IFERROR('Data Sheet'!I65-SUM('Data Sheet'!I67:I69,0),0) -> 38503 | ... L48: =IFERROR('Data Sheet'!K65-SUM('Data Sheet'!K67:K69,0),0) -> 40677
B49: Total Non Current Assets | C49: =SUM(C45:C48) -> 48201 | D49: =SUM(D45:D48) -> 46389 | E49: =SUM(E45:E48) -> 49671 | F49: =SUM(F45:F48) -> 54664 | G49: =SUM(G45:G48) -> 63503 | H49: =SUM(H45:H48) -> 76559 | I49: =SUM(I45:I48) -> 86999 | J49: =SUM(J45:J48) -> 91041 | ... L49: =SUM(L45:L48) -> 96853
B51: Receivables | C51: =IFERROR('Data Sheet'!B67,0) -> 12322 | D51: =IFERROR('Data Sheet'!C67,0) -> 13142 | E51: =IFERROR('Data Sheet'!D67,0) -> 14827 | F51: =IFERROR('Data Sheet'!E67,0) -> 18487 | G51: =IFERROR('Data Sheet'!F67,0) -> 19294 | H51: =IFERROR('Data Sheet'!G67,0) -> 22698 | I51: =IFERROR('Data Sheet'!H67,0) -> 25424 | J51: =IFERROR('Data Sheet'!I67,0) -> 30193 | ... L51: =IFERROR('Data Sheet'!K67,0) -> 35234
B52: Inventory | C52: =IFERROR('Data Sheet'!B68,0) -> 0 | D52: =IFERROR('Data Sheet'!C68,0) -> 0 | E52: =IFERROR('Data Sheet'!D68,0) -> 0 | F52: =IFERROR('Data Sheet'!E68,0) -> 0 | G52: =IFERROR('Data Sheet'!F68,0) -> 0 | H52: =IFERROR('Data Sheet'!G68,0) -> 0 | I52: =IFERROR('Data Sheet'!H68,0) -> 0 | J52: =IFERROR('Data Sheet'!I68,0) -> 0 | ... L52: =IFERROR('Data Sheet'!K68,0) -> 0
B53: Cash & Bank | C53: =IFERROR('Data Sheet'!B69,0) -> 22625 | D53: =IFERROR('Data Sheet'!C69,0) -> 19818 | E53: =IFERROR('Data Sheet'!D69,0) -> 19568 | F53: =IFERROR('Data Sheet'!E69,0) -> 18649 | G53: =IFERROR('Data Sheet'!F69,0) -> 24714 | H53: =IFERROR('Data Sheet'!G69,0) -> 17472 | I53: =IFERROR('Data Sheet'!H69,0) -> 12173 | J53: =IFERROR('Data Sheet'!I69,0) -> 14786 | ... L53: =IFERROR('Data Sheet'!K69,0) -> 22201
B54: Total Current Assets | C54: =SUM(C51:C53) -> 34947 | D54: =SUM(D51:D53) -> 32960 | E54: =SUM(E51:E53) -> 34395 | F54: =SUM(F51:F53) -> 37136 | G54: =SUM(G51:G53) -> 44008 | H54: =SUM(H51:H53) -> 40170 | I54: =SUM(I51:I53) -> 37597 | J54: =SUM(J51:J53) -> 44979 | ... L54: =SUM(L51:L53) -> 57435
B56: Total Assets | C56: =SUM(C49,C54) -> 83148 | D56: =SUM(D49,D54) -> 79349 | E56: =SUM(E49,E54) -> 84066 | F56: =SUM(F49,F54) -> 91800 | G56: =SUM(G49,G54) -> 107511 | H56: =SUM(H49,H54) -> 116729 | I56: =SUM(I49,I54) -> 124596 | J56: =SUM(J49,J54) -> 136020 | ... L56: =SUM(L49,L54) -> 154288
B57: Check | C57: =IF(C56=C43,TRUE,FALSE) -> TRUE | D57: =IF(D56=D43,TRUE,FALSE) -> TRUE | E57: =IF(E56=E43,TRUE,FALSE) -> TRUE | F57: =IF(F56=F43,TRUE,FALSE) -> TRUE | G57: =IF(G56=G43,TRUE,FALSE) -> TRUE | H57: =IF(H56=H43,TRUE,FALSE) -> TRUE | I57: =IF(I56=I43,TRUE,FALSE) -> TRUE | J57: =IF(J56=J43,TRUE,FALSE) -> TRUE | ... L57: =IF(L56=L43,TRUE,FALSE) -> TRUE
A59: # | B59: Cash Flow Statement
B62: Cash from Operating Activity | C62: =IFERROR('Data Sheet'!B82,0) -> 11531 | D62: =IFERROR('Data Sheet'!C82,0) -> 13218 | E62: =IFERROR('Data Sheet'!D82,0) -> 14841 | F62: =IFERROR('Data Sheet'!E82,0) -> 17003 | G62: =IFERROR('Data Sheet'!F82,0) -> 23224 | H62: =IFERROR('Data Sheet'!G82,0) -> 23885 | I62: =IFERROR('Data Sheet'!H82,0) -> 22467 | J62: =IFERROR('Data Sheet'!I82,0) -> 25210 | ... L62: =IFERROR('Data Sheet'!K82,0) -> 33986
B63: Cash from Investing Activity | C63: =IFERROR('Data Sheet'!B83,0) -> -14664 | D63: =IFERROR('Data Sheet'!C83,0) -> 4533 | E63: =IFERROR('Data Sheet'!D83,0) -> -632 | F63: =IFERROR('Data Sheet'!E83,0) -> -331 | G63: =IFERROR('Data Sheet'!F83,0) -> -7373 | H63: =IFERROR('Data Sheet'!G83,0) -> -6485 | I63: =IFERROR('Data Sheet'!H83,0) -> -1071 | J63: =IFERROR('Data Sheet'!I83,0) -> -5093 | ... L63: =IFERROR('Data Sheet'!K83,0) -> 3546
B64: Cash from Financing Activity | C64: =IFERROR('Data Sheet'!B84,0) -> -6939 | D64: =IFERROR('Data Sheet'!C84,0) -> -20505 | E64: =IFERROR('Data Sheet'!D84,0) -> -14512 | F64: =IFERROR('Data Sheet'!E84,0) -> -17591 | G64: =IFERROR('Data Sheet'!F84,0) -> -9786 | H64: =IFERROR('Data Sheet'!G84,0) -> -24642 | I64: =IFERROR('Data Sheet'!H84,0) -> -26695 | J64: =IFERROR('Data Sheet'!I84,0) -> -17504 | ... L64: =IFERROR('Data Sheet'!K84,0) -> -39786
B66: Net Cash Flow | C66: =IFERROR('Data Sheet'!B85,0) -> -10072 | D66: =IFERROR('Data Sheet'!C85,0) -> -2754 | E66: =IFERROR('Data Sheet'!D85,0) -> -303 | F66: =IFERROR('Data Sheet'!E85,0) -> -919 | G66: =IFERROR('Data Sheet'!F85,0) -> 6065 | H66: =IFERROR('Data Sheet'!G85,0) -> -7242 | I66: =IFERROR('Data Sheet'!H85,0) -> -5299 | J66: =IFERROR('Data Sheet'!I85,0) -> 2613 | ... L66: =IFERROR('Data Sheet'!K85,0) -> -2254
B68: Note/ Key Assumptions

Sheet Data Sheet
A1: COMPANY NAME | B1: INFOSYS LTD | E1: =IF(B2<>B3, "A NEW VERSION OF THE WORKSHEET IS AVAILABLE", "")
A2: LATEST VERSION | B2: 2.1 | E2: PLEASE DO NOT MAKE ANY CHANGES TO THIS SHEET
A3: CURRENT VERSION | B3: 2.1
A5: META
A6: Number of shares | B6: =IF(B9>0, B9/B8, 0) -> 405.80565
A7: Face Value | B7: 5
A8: Current Price | B8: 1115.3
A9: Market Capitalization | B9: 452595.04
A15: PROFIT & LOSS
A16: Report Date | B16: 42825 | C16: 43190 | D16: 43555 | E16: 43921 | F16: 44286 | G16: 44651 | H16: 45016 | I16: 45382 | J16: 45747 | K16: 46112
A17: Sales | B17: 68484 | C17: 70522 | D17: 82675 | E17: 90791 | F17: 100472 | G17: 121641 | H17: 146767 | I17: 153670 | J17: 162990 | K17: 178650
A18: Raw Material Cost
A19: Change in Inventory
A20: Power and Fuel | B20: 228 | C20: 207 | D20: 221 | E20: 229 | F20: 143 | G20: 132 | H20: 176 | I20: 199 | J20: 222 | K20: 223
A21: Other Mfr. Exp | B21: 6712 | C21: 7286 | D21: 9902 | E21: 11086 | F21: 12800 | G21: 20690 | H21: 26330 | I21: 27195 | J21: 30395 | K21: 32922
A22: Employee Cost | B22: 37669 | C22: 38902 | D22: 45323 | E22: 50895 | F22: 55547 | G22: 63997 | H22: 78374 | I22: 82636 | J22: 85968 | K22: 95112
A23: Selling and admin | B23: 4584 | C23: 4585 | D23: 5553 | E23: 5375 | F23: 3194 | G23: 4305 | H23: 5300 | I23: 5705 | J23: 6039 | K23: 6784
A24: Other Expenses | B24: 687 | C24: 720 | D24: 1506 | E24: 939 | F24: 899 | G24: 1026 | H24: 1457 | I24: 1510 | J24: 1130 | K24: 1329
A25: Other Income | B25: 3050 | C25: 3311 | D25: 2882 | E25: 2803 | F25: 2201 | G25: 2295 | H25: 2701 | I25: 4711 | J25: 3600 | K25: 3033
A26: Depreciation | B26: 1703 | C26: 1863 | D26: 2011 | E26: 2893 | F26: 3267 | G26: 3476 | H26: 4225 | I26: 4678 | J26: 4812 | K26: 4902
A27: Interest | E27: 170 | F27: 195 | G27: 200 | H27: 284 | I27: 470 | J27: 416 | K27: 416
A28: Profit before tax | B28: 19951 | C28: 20270 | D28: 21041 | E28: 22007 | F28: 26628 | G28: 30110 | H28: 33322 | I28: 35988 | J28: 37608 | K28: 39995
A29: Tax | B29: 5598 | C29: 4241 | D29: 5631 | E29: 5368 | F29: 7205 | G29: 7964 | H29: 9214 | I29: 9740 | J29: 10858 | K29: 10521
A30: Net profit | B30: 14353 | C30: 16029 | D30: 15404 | E30: 16594 | F30: 19351 | G30: 22110 | H30: 24095 | I30: 26233 | J30: 26713 | K30: 29440
A31: Dividend Amount | B31: 5891.6 | C31: 9465.6 | D31: 9222.5 | E31: 7427 | F31: 11469.6 | G31: 13007.6 | H31: 14069.2 | I31: 19053.2 | J31: 17827.8 | K31: 19430.4
A40: Quarters
A41: Report Date | B41: 45382 | C41: 45473 | D41: 45565 | E41: 45657 | F41: 45747 | G41: 45838 | H41: 45930 | I41: 46022 | J41: 46112 | K41: 46203
A42: Sales | B42: 37923 | C42: 39315 | D42: 40986 | E42: 41764 | F42: 40925 | G42: 42279 | H42: 44490 | I42: 45479 | J42: 46402 | K42: 48211
A43: Expenses | B43: 29139 | C43: 29878 | D43: 31177 | E43: 31649 | F43: 31051 | G43: 32336 | H43: 33955 | I43: 34845 | J43: 35235 | K43: 36802
A44: Other Income | B44: 2729 | C44: 838 | D44: 712 | E44: 859 | F44: 1190 | G44: 1042 | H44: 982 | I44: -150 | J44: 1159 | K44: 984
A45: Depreciation | B45: 1163 | C45: 1149 | D45: 1160 | E45: 1203 | F45: 1299 | G45: 1140 | H45: 1182 | I45: 1155 | J45: 1424 | K45: 1246
A46: Interest | B46: 110 | C46: 105 | D46: 108 | E46: 101 | F46: 102 | G46: 105 | H46: 106 | I46: 100 | J46: 105 | K46: 119
A47: Profit before tax | B47: 10240 | C47: 9021 | D47: 9253 | E47: 9670 | F47: 9663 | G47: 9740 | H47: 10229 | I47: 9229 | J47: 10797 | K47: 11028
A48: Tax | B48: 2265 | C48: 2647 | D48: 2737 | E48: 2848 | F48: 2625 | G48: 2816 | H48: 2854 | I48: 2563 | J48: 2288 | K48: 3253
A49: Net profit | B49: 7969 | C49: 6368 | D49: 6506 | E49: 6806 | F49: 7033 | G49: 6921 | H49: 7364 | I49: 6654 | J49: 8501 | K49: 7769
A50: Operating Profit | B50: 8784 | C50: 9437 | D50: 9809 | E50: 10115 | F50: 9874 | G50: 9943 | H50: 10535 | I50: 10634 | J50: 11167 | K50: 11409
A55: BALANCE SHEET
A56: Report Date | B56: 42825 | C56: 43190 | D56: 43555 | E56: 43921 | F56: 44286 | G56: 44651 | H56: 45016 | I56: 45382 | J56: 45747 | K56: 46112
A57: Equity Share Capital | B57: 1144 | C57: 1088 | D57: 2170 | E57: 2122 | F57: 2124 | G57: 2098 | H57: 2069 | I57: 2071 | J57: 2073 | K57: 2024
A58: Reserves | B58: 67838 | C58: 63835 | D58: 62778 | E58: 63328 | F58: 74227 | G58: 73252 | H58: 73338 | I58: 86045 | J58: 93745 | K58: 90828
A59: Borrowings | E59: 4633 | F59: 5325 | G59: 5474 | H59: 8299 | I59: 8359 | J59: 8227 | K59: 9176
A60: Other Liabilities | B60: 14166 | C60: 14426 | D60: 19118 | E60: 21717 | F60: 25835 | G60: 35905 | H60: 40890 | I60: 39545 | J60: 43750 | K60: 52260
A61: Total | B61: 83148 | C61: 79349 | D61: 84066 | E61: 91800 | F61: 107511 | G61: 116729 | H61: 124596 | I61: 136020 | J61: 147795 | K61: 154288
A62: Net Block | B62: 14179 | C62: 12574 | D62: 15710 | E62: 23789 | F62: 25505 | G62: 25800 | H62: 29225 | I62: 27622 | J62: 30961 | K62: 33770
A63: Capital Work in Progress | B63: 1365 | C63: 1606 | D63: 1388 | E63: 954 | F63: 922 | G63: 416 | H63: 288 | I63: 293 | J63: 814 | K63: 526
A64: Investments | B64: 16423 | C64: 12163 | D64: 11261 | E64: 8792 | F64: 14205 | G64: 20324 | H64: 19478 | I64: 24623 | J64: 23541 | K64: 21880
A65: Other Assets | B65: 51181 | C65: 53006 | D65: 55707 | E65: 58265 | F65: 66879 | G65: 70189 | H65: 75605 | I65: 83482 | J65: 92479 | K65: 98112
A66: Total | B66: 83148 | C66: 79349 | D66: 84066 | E66: 91800 | F66: 107511 | G66: 116729 | H66: 124596 | I66: 136020 | J66: 147795 | K66: 154288
A67: Receivables | B67: 12322 | C67: 13142 | D67: 14827 | E67: 18487 | F67: 19294 | G67: 22698 | H67: 25424 | I67: 30193 | J67: 31158 | K67: 35234
A68: Inventory
A69: Cash & Bank | B69: 22625 | C69: 19818 | D69: 19568 | E69: 18649 | F69: 24714 | G69: 17472 | H69: 12173 | I69: 14786 | J69: 24455 | K69: 22201
A70: No. of Equity Shares | B70: 2285655150 | C70: 2173312301 | D70: 4335954462 | E70: 4240753210 | F70: 4245146114 | G70: 4193012929 | H70: 4136387925 | I70: 4139950635 | J70: 4143607528 | K70: 4046940812
A71: New Bonus Shares | D71: 2184191490
A72: Face value | B72: 5 | C72: 5 | D72: 5 | E72: 5 | F72: 5 | G72: 5 | H72: 5 | I72: 5 | J72: 5 | K72: 5
A80: CASH FLOW:
A81: Report Date | B81: 42825 | C81: 43190 | D81: 43555 | E81: 43921 | F81: 44286 | G81: 44651 | H81: 45016 | I81: 45382 | J81: 45747 | K81: 46112
A82: Cash from Operating Activity | B82: 11531 | C82: 13218 | D82: 14841 | E82: 17003 | F82: 23224 | G82: 23885 | H82: 22467 | I82: 25210 | J82: 35694 | K82: 33986
A83: Cash from Investing Activity | B83: -14664 | C83: 4533 | D83: -632 | E83: -331 | F83: -7373 | G83: -6485 | H83: -1071 | I83: -5093 | J83: -1864 | K83: 3546
A84: Cash from Financing Activity | B84: -6939 | C84: -20505 | D84: -14512 | E84: -17591 | F84: -9786 | G84: -24642 | H84: -26695 | I84: -17504 | J84: -24161 | K84: -39786
A85: Net Cash Flow | B85: -10072 | C85: -2754 | D85: -303 | E85: -919 | F85: 6065 | G85: -7242 | H85: -5299 | I85: 2613 | J85: 9669 | K85: -2254
A90: PRICE: | B90: 511.13 | C90: 565.9 | D90: 743.85 | E90: 641.5 | F90: 1368.05 | G90: 1906.85 | H90: 1427.95 | I90: 1498.05 | J90: 1570.65 | K90: 1250.6
A92: DERIVED:
A93: Adjusted Equity Shares in Cr | B93: 459.39 | C93: 436.82 | D93: 436.89 | E93: 425.9 | F93: 426.07 | G93: 420.67 | H93: 414.86 | I93: 415.09 | J93: 415.33 | K93: 405.56
